[
  {
    "data_id": 44569537, 
    "sample_name": "BXD100", 
    "sample_name_2": "BXD100", 
    "se": 0.488, 
    "value": 7.487
  }, 
  {
    "data_id": 44569537, 
    "sample_name": "BXD101", 
    "sample_name_2": "BXD101", 
    "value": 7.123
  }, 
  {
    "data_id": 44569537, 
    "sample_name": "BXD102", 
    "sample_name_2": "BXD102", 
    "value": 7.685
  }, 
  {
    "data_id": 44569537, 
    "sample_name": "BXD34", 
    "sample_name_2": "BXD34", 
    "value": 6.954
  }, 
  {
    "data_id": 44569537, 
    "sample_name": "BXD43", 
    "sample_name_2": "BXD43", 
    "se": 0.288, 
    "value": 7.088
  }, 
  {
    "data_id": 44569537, 
    "sample_name": "BXD44", 
    "sample_name_2": "BXD44", 
    "se": 0.247, 
    "value": 7.1
  }, 
  {
    "data_id": 44569537, 
    "sample_name": "BXD45", 
    "sample_name_2": "BXD45", 
    "value": 6.935
  }, 
  {
    "data_id": 44569537, 
    "sample_name": "BXD48a", 
    "sample_name_2": "BXD96", 
    "value": 7.014
  }, 
  {
    "data_id": 44569537, 
    "sample_name": "BXD51", 
    "sample_name_2": "BXD51", 
    "value": 7.236
  }, 
  {
    "data_id": 44569537, 
    "sample_name": "BXD55", 
    "sample_name_2": "BXD55", 
    "value": 6.844
  }, 
  {
    "data_id": 44569537, 
    "sample_name": "BXD60", 
    "sample_name_2": "BXD60", 
    "se": 0.101, 
    "value": 7.124
  }, 
  {
    "data_id": 44569537, 
    "sample_name": "BXD61", 
    "sample_name_2": "BXD61", 
    "value": 6.807
  }, 
  {
    "data_id": 44569537, 
    "sample_name": "BXD62", 
    "sample_name_2": "BXD62", 
    "se": 0.33, 
    "value": 7.29
  }, 
  {
    "data_id": 44569537, 
    "sample_name": "BXD65a", 
    "sample_name_2": "BXD97", 
    "se": 0.025, 
    "value": 7.306
  }, 
  {
    "data_id": 44569537, 
    "sample_name": "BXD66", 
    "sample_name_2": "BXD66", 
    "se": 0.383, 
    "value": 7.134
  }, 
  {
    "data_id": 44569537, 
    "sample_name": "BXD68", 
    "sample_name_2": "BXD68", 
    "value": 7.615
  }, 
  {
    "data_id": 44569537, 
    "sample_name": "BXD70", 
    "sample_name_2": "BXD70", 
    "se": 0.261, 
    "value": 7.274
  }, 
  {
    "data_id": 44569537, 
    "sample_name": "BXD73", 
    "sample_name_2": "BXD73", 
    "se": 0.269, 
    "value": 7.252
  }, 
  {
    "data_id": 44569537, 
    "sample_name": "BXD73a", 
    "sample_name_2": "BXD80", 
    "value": 6.95
  }, 
  {
    "data_id": 44569537, 
    "sample_name": "BXD75", 
    "sample_name_2": "BXD75", 
    "se": 0.298, 
    "value": 7.108
  }, 
  {
    "data_id": 44569537, 
    "sample_name": "BXD79", 
    "sample_name_2": "BXD79", 
    "value": 7.16
  }, 
  {
    "data_id": 44569537, 
    "sample_name": "BXD83", 
    "sample_name_2": "BXD83", 
    "se": 0.197, 
    "value": 7.142
  }, 
  {
    "data_id": 44569537, 
    "sample_name": "BXD84", 
    "sample_name_2": "BXD84", 
    "value": 7.181
  }, 
  {
    "data_id": 44569537, 
    "sample_name": "BXD87", 
    "sample_name_2": "BXD87", 
    "value": 7.042
  }, 
  {
    "data_id": 44569537, 
    "sample_name": "BXD9", 
    "sample_name_2": "BXD9", 
    "value": 7.357
  }, 
  {
    "data_id": 44569537, 
    "sample_name": "BXD90", 
    "sample_name_2": "BXD90", 
    "value": 6.869
  }, 
  {
    "data_id": 44569537, 
    "sample_name": "BXD99", 
    "sample_name_2": "BXD99", 
    "value": 7.363
  }
]
