[
  {
    "data_id": 71803031, 
    "sample_name": "B6D2F1", 
    "sample_name_2": "B6D2F1", 
    "se": 0.17112, 
    "value": 10.54
  }, 
  {
    "data_id": 71803031, 
    "sample_name": "BXD1", 
    "sample_name_2": "BXD1", 
    "se": 0.393151, 
    "value": 10.044
  }, 
  {
    "data_id": 71803031, 
    "sample_name": "BXD100", 
    "sample_name_2": "BXD100", 
    "se": 0.152735, 
    "value": 10.436
  }, 
  {
    "data_id": 71803031, 
    "sample_name": "BXD101", 
    "sample_name_2": "BXD101", 
    "se": 0.420021, 
    "value": 10.321
  }, 
  {
    "data_id": 71803031, 
    "sample_name": "BXD102", 
    "sample_name_2": "BXD102", 
    "se": 0.0459619, 
    "value": 10.4765
  }, 
  {
    "data_id": 71803031, 
    "sample_name": "BXD11", 
    "sample_name_2": "BXD11", 
    "se": 0.138593, 
    "value": 10.107
  }, 
  {
    "data_id": 71803031, 
    "sample_name": "BXD12", 
    "sample_name_2": "BXD12", 
    "se": 0.0254558, 
    "value": 10.563
  }, 
  {
    "data_id": 71803031, 
    "sample_name": "BXD14", 
    "sample_name_2": "BXD14", 
    "se": 0.0544472, 
    "value": 10.4425
  }, 
  {
    "data_id": 71803031, 
    "sample_name": "BXD24", 
    "sample_name_2": "BXD24", 
    "se": 0.302642, 
    "value": 10.196
  }, 
  {
    "data_id": 71803031, 
    "sample_name": "BXD27", 
    "sample_name_2": "BXD27", 
    "se": 0.0827315, 
    "value": 10.5175
  }, 
  {
    "data_id": 71803031, 
    "sample_name": "BXD29", 
    "sample_name_2": "BXD29", 
    "se": 0.253144, 
    "value": 10.38
  }, 
  {
    "data_id": 71803031, 
    "sample_name": "BXD31", 
    "sample_name_2": "BXD31", 
    "se": 0.1393, 
    "value": 10.3675
  }, 
  {
    "data_id": 71803031, 
    "sample_name": "BXD32", 
    "sample_name_2": "BXD32", 
    "se": 0.0155563, 
    "value": 10.31
  }, 
  {
    "data_id": 71803031, 
    "sample_name": "BXD34", 
    "sample_name_2": "BXD34", 
    "se": 0.169776, 
    "value": 10.399
  }, 
  {
    "data_id": 71803031, 
    "sample_name": "BXD39", 
    "sample_name_2": "BXD39", 
    "se": 0.132936, 
    "value": 9.853
  }, 
  {
    "data_id": 71803031, 
    "sample_name": "BXD40", 
    "sample_name_2": "BXD40", 
    "se": 0.0339411, 
    "value": 10.211
  }, 
  {
    "data_id": 71803031, 
    "sample_name": "BXD42", 
    "sample_name_2": "BXD42", 
    "se": 0.0155563, 
    "value": 10.152
  }, 
  {
    "data_id": 71803031, 
    "sample_name": "BXD43", 
    "sample_name_2": "BXD43", 
    "se": 0.0459909, 
    "value": 10.4193
  }, 
  {
    "data_id": 71803031, 
    "sample_name": "BXD44", 
    "sample_name_2": "BXD44", 
    "se": 0.23027, 
    "value": 10.2998
  }, 
  {
    "data_id": 71803031, 
    "sample_name": "BXD45", 
    "sample_name_2": "BXD45", 
    "se": 0.178898, 
    "value": 10.4575
  }, 
  {
    "data_id": 71803031, 
    "sample_name": "BXD48", 
    "sample_name_2": "BXD48", 
    "se": 0.0445477, 
    "value": 10.4085
  }, 
  {
    "data_id": 71803031, 
    "sample_name": "BXD49", 
    "sample_name_2": "BXD49", 
    "value": 10.191
  }, 
  {
    "data_id": 71803031, 
    "sample_name": "BXD50", 
    "sample_name_2": "BXD50", 
    "se": 0.511945, 
    "value": 10.033
  }, 
  {
    "data_id": 71803031, 
    "sample_name": "BXD56", 
    "sample_name_2": "BXD56", 
    "se": 0.113475, 
    "value": 10.515
  }, 
  {
    "data_id": 71803031, 
    "sample_name": "BXD60", 
    "sample_name_2": "BXD60", 
    "se": 0.620133, 
    "value": 9.8625
  }, 
  {
    "data_id": 71803031, 
    "sample_name": "BXD62", 
    "sample_name_2": "BXD62", 
    "se": 0.0551543, 
    "value": 10.46
  }, 
  {
    "data_id": 71803031, 
    "sample_name": "BXD63", 
    "sample_name_2": "BXD63", 
    "se": 0.372645, 
    "value": 10.3855
  }, 
  {
    "data_id": 71803031, 
    "sample_name": "BXD65", 
    "sample_name_2": "BXD65", 
    "se": 0.345068, 
    "value": 10.522
  }, 
  {
    "data_id": 71803031, 
    "sample_name": "BXD65a", 
    "sample_name_2": "BXD97", 
    "se": 0.275772, 
    "value": 10.469
  }, 
  {
    "data_id": 71803031, 
    "sample_name": "BXD65b", 
    "sample_name_2": "BXD92", 
    "se": 0.265165, 
    "value": 10.5635
  }, 
  {
    "data_id": 71803031, 
    "sample_name": "BXD68", 
    "sample_name_2": "BXD68", 
    "se": 0.545886, 
    "value": 10.094
  }, 
  {
    "data_id": 71803031, 
    "sample_name": "BXD69", 
    "sample_name_2": "BXD69", 
    "se": 0.00494975, 
    "value": 10.2745
  }, 
  {
    "data_id": 71803031, 
    "sample_name": "BXD70", 
    "sample_name_2": "BXD70", 
    "se": 0.236174, 
    "value": 10.628
  }, 
  {
    "data_id": 71803031, 
    "sample_name": "BXD71", 
    "sample_name_2": "BXD71", 
    "se": 0.526795, 
    "value": 10.1725
  }, 
  {
    "data_id": 71803031, 
    "sample_name": "BXD73", 
    "sample_name_2": "BXD73", 
    "se": 0.207889, 
    "value": 10.053
  }, 
  {
    "data_id": 71803031, 
    "sample_name": "BXD73a", 
    "sample_name_2": "BXD80", 
    "se": 0.0523259, 
    "value": 10.151
  }, 
  {
    "data_id": 71803031, 
    "sample_name": "BXD73b", 
    "sample_name_2": "BXD103", 
    "se": 0.317491, 
    "value": 10.2805
  }, 
  {
    "data_id": 71803031, 
    "sample_name": "BXD75", 
    "sample_name_2": "BXD75", 
    "se": 0.170413, 
    "value": 10.2055
  }, 
  {
    "data_id": 71803031, 
    "sample_name": "BXD79", 
    "sample_name_2": "BXD79", 
    "se": 0.291328, 
    "value": 10.55
  }, 
  {
    "data_id": 71803031, 
    "sample_name": "BXD83", 
    "sample_name_2": "BXD83", 
    "se": 0.240416, 
    "value": 10.235
  }, 
  {
    "data_id": 71803031, 
    "sample_name": "BXD84", 
    "sample_name_2": "BXD84", 
    "se": 0.216375, 
    "value": 9.96
  }, 
  {
    "data_id": 71803031, 
    "sample_name": "BXD85", 
    "sample_name_2": "BXD85", 
    "se": 0.946816, 
    "value": 9.9905
  }, 
  {
    "data_id": 71803031, 
    "sample_name": "BXD87", 
    "sample_name_2": "BXD87", 
    "se": 0.0756604, 
    "value": 10.4835
  }, 
  {
    "data_id": 71803031, 
    "sample_name": "BXD89", 
    "sample_name_2": "BXD89", 
    "se": 0.0388909, 
    "value": 10.5655
  }, 
  {
    "data_id": 71803031, 
    "sample_name": "BXD90", 
    "sample_name_2": "BXD90", 
    "se": 0.0473762, 
    "value": 10.5005
  }, 
  {
    "data_id": 71803031, 
    "sample_name": "BXD95", 
    "sample_name_2": "BXD95", 
    "se": 0.471559, 
    "value": 9.981
  }, 
  {
    "data_id": 71803031, 
    "sample_name": "BXD99", 
    "sample_name_2": "BXD99", 
    "se": 0.81883, 
    "value": 9.827
  }, 
  {
    "data_id": 71803031, 
    "sample_name": "C57BL/6J", 
    "sample_name_2": "C57BL/6J", 
    "se": 0.0841619, 
    "value": 10.3565
  }, 
  {
    "data_id": 71803031, 
    "sample_name": "D2B6F1", 
    "sample_name_2": "D2B6F1", 
    "se": 0.298399, 
    "value": 10.618
  }, 
  {
    "data_id": 71803031, 
    "sample_name": "DBA/2J", 
    "sample_name_2": "DBA/2J", 
    "se": 0.245831, 
    "value": 10.6193
  }
]
