[
  {
    "data_id": 71649581, 
    "sample_name": "B6D2F1", 
    "sample_name_2": "B6D2F1", 
    "se": 0.152028, 
    "value": 7.5355
  }, 
  {
    "data_id": 71649581, 
    "sample_name": "BXD1", 
    "sample_name_2": "BXD1", 
    "se": 0.182434, 
    "value": 7.781
  }, 
  {
    "data_id": 71649581, 
    "sample_name": "BXD100", 
    "sample_name_2": "BXD100", 
    "se": 0.26163, 
    "value": 7.507
  }, 
  {
    "data_id": 71649581, 
    "sample_name": "BXD101", 
    "sample_name_2": "BXD101", 
    "se": 1.27138, 
    "value": 7.399
  }, 
  {
    "data_id": 71649581, 
    "sample_name": "BXD102", 
    "sample_name_2": "BXD102", 
    "se": 0.128693, 
    "value": 7.368
  }, 
  {
    "data_id": 71649581, 
    "sample_name": "BXD11", 
    "sample_name_2": "BXD11", 
    "se": 0.121622, 
    "value": 7.641
  }, 
  {
    "data_id": 71649581, 
    "sample_name": "BXD12", 
    "sample_name_2": "BXD12", 
    "se": 0.026163, 
    "value": 7.6655
  }, 
  {
    "data_id": 71649581, 
    "sample_name": "BXD14", 
    "sample_name_2": "BXD14", 
    "se": 0.147078, 
    "value": 7.744
  }, 
  {
    "data_id": 71649581, 
    "sample_name": "BXD24", 
    "sample_name_2": "BXD24", 
    "se": 0.140714, 
    "value": 7.4305
  }, 
  {
    "data_id": 71649581, 
    "sample_name": "BXD27", 
    "sample_name_2": "BXD27", 
    "se": 0.0947523, 
    "value": 7.618
  }, 
  {
    "data_id": 71649581, 
    "sample_name": "BXD29", 
    "sample_name_2": "BXD29", 
    "se": 0.072832, 
    "value": 7.6365
  }, 
  {
    "data_id": 71649581, 
    "sample_name": "BXD31", 
    "sample_name_2": "BXD31", 
    "se": 0.104652, 
    "value": 7.364
  }, 
  {
    "data_id": 71649581, 
    "sample_name": "BXD32", 
    "sample_name_2": "BXD32", 
    "se": 0.167584, 
    "value": 7.7805
  }, 
  {
    "data_id": 71649581, 
    "sample_name": "BXD34", 
    "sample_name_2": "BXD34", 
    "se": 0.438138, 
    "value": 7.773
  }, 
  {
    "data_id": 71649581, 
    "sample_name": "BXD39", 
    "sample_name_2": "BXD39", 
    "se": 0.11738, 
    "value": 7.782
  }, 
  {
    "data_id": 71649581, 
    "sample_name": "BXD40", 
    "sample_name_2": "BXD40", 
    "se": 0.34224, 
    "value": 7.523
  }, 
  {
    "data_id": 71649581, 
    "sample_name": "BXD42", 
    "sample_name_2": "BXD42", 
    "se": 0.155563, 
    "value": 8.09
  }, 
  {
    "data_id": 71649581, 
    "sample_name": "BXD43", 
    "sample_name_2": "BXD43", 
    "se": 0.121114, 
    "value": 7.66067
  }, 
  {
    "data_id": 71649581, 
    "sample_name": "BXD44", 
    "sample_name_2": "BXD44", 
    "se": 0.221463, 
    "value": 7.539
  }, 
  {
    "data_id": 71649581, 
    "sample_name": "BXD45", 
    "sample_name_2": "BXD45", 
    "se": 0.210011, 
    "value": 7.1115
  }, 
  {
    "data_id": 71649581, 
    "sample_name": "BXD48", 
    "sample_name_2": "BXD48", 
    "se": 0.10253, 
    "value": 7.6315
  }, 
  {
    "data_id": 71649581, 
    "sample_name": "BXD49", 
    "sample_name_2": "BXD49", 
    "value": 7.237
  }, 
  {
    "data_id": 71649581, 
    "sample_name": "BXD50", 
    "sample_name_2": "BXD50", 
    "se": 0.405172, 
    "value": 8.0165
  }, 
  {
    "data_id": 71649581, 
    "sample_name": "BXD56", 
    "sample_name_2": "BXD56", 
    "se": 0.295237, 
    "value": 7.54467
  }, 
  {
    "data_id": 71649581, 
    "sample_name": "BXD60", 
    "sample_name_2": "BXD60", 
    "se": 0.0622254, 
    "value": 7.519
  }, 
  {
    "data_id": 71649581, 
    "sample_name": "BXD62", 
    "sample_name_2": "BXD62", 
    "se": 0.21991, 
    "value": 7.1735
  }, 
  {
    "data_id": 71649581, 
    "sample_name": "BXD63", 
    "sample_name_2": "BXD63", 
    "se": 0.138593, 
    "value": 7.466
  }, 
  {
    "data_id": 71649581, 
    "sample_name": "BXD65", 
    "sample_name_2": "BXD65", 
    "se": 0.304763, 
    "value": 7.5475
  }, 
  {
    "data_id": 71649581, 
    "sample_name": "BXD65a", 
    "sample_name_2": "BXD97", 
    "se": 0.385373, 
    "value": 7.5075
  }, 
  {
    "data_id": 71649581, 
    "sample_name": "BXD65b", 
    "sample_name_2": "BXD92", 
    "se": 0.189505, 
    "value": 7.488
  }, 
  {
    "data_id": 71649581, 
    "sample_name": "BXD68", 
    "sample_name_2": "BXD68", 
    "se": 0.0622254, 
    "value": 7.862
  }, 
  {
    "data_id": 71649581, 
    "sample_name": "BXD69", 
    "sample_name_2": "BXD69", 
    "se": 0.388202, 
    "value": 7.6025
  }, 
  {
    "data_id": 71649581, 
    "sample_name": "BXD70", 
    "sample_name_2": "BXD70", 
    "se": 0.146371, 
    "value": 7.2255
  }, 
  {
    "data_id": 71649581, 
    "sample_name": "BXD71", 
    "sample_name_2": "BXD71", 
    "se": 0.125158, 
    "value": 7.9045
  }, 
  {
    "data_id": 71649581, 
    "sample_name": "BXD73", 
    "sample_name_2": "BXD73", 
    "se": 0.434871, 
    "value": 7.5145
  }, 
  {
    "data_id": 71649581, 
    "sample_name": "BXD73a", 
    "sample_name_2": "BXD80", 
    "se": 0.216375, 
    "value": 7.191
  }, 
  {
    "data_id": 71649581, 
    "sample_name": "BXD73b", 
    "sample_name_2": "BXD103", 
    "se": 0.279307, 
    "value": 6.8515
  }, 
  {
    "data_id": 71649581, 
    "sample_name": "BXD75", 
    "sample_name_2": "BXD75", 
    "se": 0.133643, 
    "value": 7.3135
  }, 
  {
    "data_id": 71649581, 
    "sample_name": "BXD79", 
    "sample_name_2": "BXD79", 
    "se": 0.345068, 
    "value": 7.26
  }, 
  {
    "data_id": 71649581, 
    "sample_name": "BXD83", 
    "sample_name_2": "BXD83", 
    "se": 0.0685894, 
    "value": 7.6055
  }, 
  {
    "data_id": 71649581, 
    "sample_name": "BXD84", 
    "sample_name_2": "BXD84", 
    "se": 0.239709, 
    "value": 7.6655
  }, 
  {
    "data_id": 71649581, 
    "sample_name": "BXD85", 
    "sample_name_2": "BXD85", 
    "se": 0.282843, 
    "value": 7.622
  }, 
  {
    "data_id": 71649581, 
    "sample_name": "BXD87", 
    "sample_name_2": "BXD87", 
    "se": 0.201525, 
    "value": 7.7265
  }, 
  {
    "data_id": 71649581, 
    "sample_name": "BXD89", 
    "sample_name_2": "BXD89", 
    "se": 0.0190919, 
    "value": 7.4835
  }, 
  {
    "data_id": 71649581, 
    "sample_name": "BXD90", 
    "sample_name_2": "BXD90", 
    "se": 0.174655, 
    "value": 7.9115
  }, 
  {
    "data_id": 71649581, 
    "sample_name": "BXD95", 
    "sample_name_2": "BXD95", 
    "se": 0.229845, 
    "value": 7.95967
  }, 
  {
    "data_id": 71649581, 
    "sample_name": "BXD99", 
    "sample_name_2": "BXD99", 
    "se": 0.212132, 
    "value": 7.853
  }, 
  {
    "data_id": 71649581, 
    "sample_name": "C57BL/6J", 
    "sample_name_2": "C57BL/6J", 
    "se": 0.161812, 
    "value": 7.62325
  }, 
  {
    "data_id": 71649581, 
    "sample_name": "D2B6F1", 
    "sample_name_2": "D2B6F1", 
    "se": 0.0806102, 
    "value": 7.433
  }, 
  {
    "data_id": 71649581, 
    "sample_name": "DBA/2J", 
    "sample_name_2": "DBA/2J", 
    "se": 0.334605, 
    "value": 7.702
  }
]
