[
  {
    "data_id": 78519487, 
    "sample_name": "BXD100", 
    "sample_name_2": "BXD100", 
    "value": 10.9133
  }, 
  {
    "data_id": 78519487, 
    "sample_name": "BXD101", 
    "sample_name_2": "BXD101", 
    "value": 11.2543
  }, 
  {
    "data_id": 78519487, 
    "sample_name": "BXD34", 
    "sample_name_2": "BXD34", 
    "value": 11.4023
  }, 
  {
    "data_id": 78519487, 
    "sample_name": "BXD43", 
    "sample_name_2": "BXD43", 
    "value": 11.7728
  }, 
  {
    "data_id": 78519487, 
    "sample_name": "BXD45", 
    "sample_name_2": "BXD45", 
    "value": 10.861
  }, 
  {
    "data_id": 78519487, 
    "sample_name": "BXD48a", 
    "sample_name_2": "BXD96", 
    "value": 10.3455
  }, 
  {
    "data_id": 78519487, 
    "sample_name": "BXD51", 
    "sample_name_2": "BXD51", 
    "value": 11.32
  }, 
  {
    "data_id": 78519487, 
    "sample_name": "BXD55", 
    "sample_name_2": "BXD55", 
    "value": 9.1473
  }, 
  {
    "data_id": 78519487, 
    "sample_name": "BXD60", 
    "sample_name_2": "BXD60", 
    "value": 11.2318
  }, 
  {
    "data_id": 78519487, 
    "sample_name": "BXD61", 
    "sample_name_2": "BXD61", 
    "value": 10.744
  }, 
  {
    "data_id": 78519487, 
    "sample_name": "BXD62", 
    "sample_name_2": "BXD62", 
    "value": 11.6138
  }, 
  {
    "data_id": 78519487, 
    "sample_name": "BXD65a", 
    "sample_name_2": "BXD97", 
    "value": 11.2223
  }, 
  {
    "data_id": 78519487, 
    "sample_name": "BXD66", 
    "sample_name_2": "BXD66", 
    "value": 10.7193
  }, 
  {
    "data_id": 78519487, 
    "sample_name": "BXD68", 
    "sample_name_2": "BXD68", 
    "value": 11.6265
  }, 
  {
    "data_id": 78519487, 
    "sample_name": "BXD70", 
    "sample_name_2": "BXD70", 
    "value": 10.6113
  }, 
  {
    "data_id": 78519487, 
    "sample_name": "BXD71", 
    "sample_name_2": "BXD71", 
    "value": 11.4997
  }, 
  {
    "data_id": 78519487, 
    "sample_name": "BXD73", 
    "sample_name_2": "BXD73", 
    "value": 10.8893
  }, 
  {
    "data_id": 78519487, 
    "sample_name": "BXD75", 
    "sample_name_2": "BXD75", 
    "value": 11.2793
  }, 
  {
    "data_id": 78519487, 
    "sample_name": "BXD83", 
    "sample_name_2": "BXD83", 
    "value": 10.8448
  }, 
  {
    "data_id": 78519487, 
    "sample_name": "BXD84", 
    "sample_name_2": "BXD84", 
    "value": 11.8225
  }, 
  {
    "data_id": 78519487, 
    "sample_name": "BXD87", 
    "sample_name_2": "BXD87", 
    "value": 11.0273
  }, 
  {
    "data_id": 78519487, 
    "sample_name": "BXD89", 
    "sample_name_2": "BXD89", 
    "value": 11.0307
  }, 
  {
    "data_id": 78519487, 
    "sample_name": "BXD90", 
    "sample_name_2": "BXD90", 
    "value": 10.6975
  }, 
  {
    "data_id": 78519487, 
    "sample_name": "BXD98", 
    "sample_name_2": "BXD98", 
    "value": 10.6387
  }, 
  {
    "data_id": 78519487, 
    "sample_name": "BXD99", 
    "sample_name_2": "BXD99", 
    "value": 11.1905
  }, 
  {
    "data_id": 78519487, 
    "sample_name": "DBA/2J", 
    "sample_name_2": "DBA/2J", 
    "value": 10.8237
  }
]
