[
  {
    "data_id": 55834419, 
    "sample_name": "BXD100", 
    "sample_name_2": "BXD100", 
    "value": 7.15
  }, 
  {
    "data_id": 55834419, 
    "sample_name": "BXD101", 
    "sample_name_2": "BXD101", 
    "value": 7.129
  }, 
  {
    "data_id": 55834419, 
    "sample_name": "BXD34", 
    "sample_name_2": "BXD34", 
    "value": 7.107
  }, 
  {
    "data_id": 55834419, 
    "sample_name": "BXD40", 
    "sample_name_2": "BXD40", 
    "value": 7.115
  }, 
  {
    "data_id": 55834419, 
    "sample_name": "BXD43", 
    "sample_name_2": "BXD43", 
    "se": 0.041, 
    "value": 7.155
  }, 
  {
    "data_id": 55834419, 
    "sample_name": "BXD44", 
    "sample_name_2": "BXD44", 
    "se": 0.036, 
    "value": 7.175
  }, 
  {
    "data_id": 55834419, 
    "sample_name": "BXD45", 
    "sample_name_2": "BXD45", 
    "se": 0.049, 
    "value": 7.148
  }, 
  {
    "data_id": 55834419, 
    "sample_name": "BXD48a", 
    "sample_name_2": "BXD96", 
    "se": 0.074, 
    "value": 7.106
  }, 
  {
    "data_id": 55834419, 
    "sample_name": "BXD51", 
    "sample_name_2": "BXD51", 
    "se": 0.009, 
    "value": 7.106
  }, 
  {
    "data_id": 55834419, 
    "sample_name": "BXD55", 
    "sample_name_2": "BXD55", 
    "se": 0.021, 
    "value": 7.119
  }, 
  {
    "data_id": 55834419, 
    "sample_name": "BXD60", 
    "sample_name_2": "BXD60", 
    "se": 0.036, 
    "value": 7.135
  }, 
  {
    "data_id": 55834419, 
    "sample_name": "BXD61", 
    "sample_name_2": "BXD61", 
    "se": 0.062, 
    "value": 7.117
  }, 
  {
    "data_id": 55834419, 
    "sample_name": "BXD62", 
    "sample_name_2": "BXD62", 
    "se": 0.012, 
    "value": 7.146
  }, 
  {
    "data_id": 55834419, 
    "sample_name": "BXD65", 
    "sample_name_2": "BXD65", 
    "value": 7.134
  }, 
  {
    "data_id": 55834419, 
    "sample_name": "BXD65a", 
    "sample_name_2": "BXD97", 
    "value": 7.18
  }, 
  {
    "data_id": 55834419, 
    "sample_name": "BXD65b", 
    "sample_name_2": "BXD92", 
    "se": 0.03, 
    "value": 7.125
  }, 
  {
    "data_id": 55834419, 
    "sample_name": "BXD66", 
    "sample_name_2": "BXD66", 
    "se": 0.011, 
    "value": 7.132
  }, 
  {
    "data_id": 55834419, 
    "sample_name": "BXD68", 
    "sample_name_2": "BXD68", 
    "se": 0.034, 
    "value": 7.125
  }, 
  {
    "data_id": 55834419, 
    "sample_name": "BXD69", 
    "sample_name_2": "BXD69", 
    "value": 7.186
  }, 
  {
    "data_id": 55834419, 
    "sample_name": "BXD70", 
    "sample_name_2": "BXD70", 
    "se": 0.003, 
    "value": 7.136
  }, 
  {
    "data_id": 55834419, 
    "sample_name": "BXD71", 
    "sample_name_2": "BXD71", 
    "se": 0.004, 
    "value": 7.124
  }, 
  {
    "data_id": 55834419, 
    "sample_name": "BXD73", 
    "sample_name_2": "BXD73", 
    "se": 0.032, 
    "value": 7.113
  }, 
  {
    "data_id": 55834419, 
    "sample_name": "BXD73a", 
    "sample_name_2": "BXD80", 
    "value": 7.146
  }, 
  {
    "data_id": 55834419, 
    "sample_name": "BXD75", 
    "sample_name_2": "BXD75", 
    "se": 0.01, 
    "value": 7.183
  }, 
  {
    "data_id": 55834419, 
    "sample_name": "BXD79", 
    "sample_name_2": "BXD79", 
    "value": 6.981
  }, 
  {
    "data_id": 55834419, 
    "sample_name": "BXD83", 
    "sample_name_2": "BXD83", 
    "se": 0.105, 
    "value": 7.094
  }, 
  {
    "data_id": 55834419, 
    "sample_name": "BXD84", 
    "sample_name_2": "BXD84", 
    "se": 0.06, 
    "value": 7.18
  }, 
  {
    "data_id": 55834419, 
    "sample_name": "BXD86", 
    "sample_name_2": "BXD86", 
    "value": 7.116
  }, 
  {
    "data_id": 55834419, 
    "sample_name": "BXD87", 
    "sample_name_2": "BXD87", 
    "se": 0.012, 
    "value": 7.126
  }, 
  {
    "data_id": 55834419, 
    "sample_name": "BXD89", 
    "sample_name_2": "BXD89", 
    "se": 0.008, 
    "value": 7.152
  }, 
  {
    "data_id": 55834419, 
    "sample_name": "BXD90", 
    "sample_name_2": "BXD90", 
    "se": 0.111, 
    "value": 7.136
  }, 
  {
    "data_id": 55834419, 
    "sample_name": "BXD95", 
    "sample_name_2": "BXD95", 
    "value": 7.139
  }, 
  {
    "data_id": 55834419, 
    "sample_name": "BXD98", 
    "sample_name_2": "BXD98", 
    "se": 0.023, 
    "value": 7.123
  }, 
  {
    "data_id": 55834419, 
    "sample_name": "BXD99", 
    "sample_name_2": "BXD99", 
    "value": 7.123
  }, 
  {
    "data_id": 55834419, 
    "sample_name": "DBA/2J", 
    "sample_name_2": "DBA/2J", 
    "se": 0.013, 
    "value": 7.127
  }
]
