[
  {
    "data_id": 71666415, 
    "sample_name": "B6D2F1", 
    "sample_name_2": "B6D2F1", 
    "se": 0.205061, 
    "value": 6.354
  }, 
  {
    "data_id": 71666415, 
    "sample_name": "BXD1", 
    "sample_name_2": "BXD1", 
    "se": 0.465983, 
    "value": 6.3695
  }, 
  {
    "data_id": 71666415, 
    "sample_name": "BXD100", 
    "sample_name_2": "BXD100", 
    "se": 0.234759, 
    "value": 5.95
  }, 
  {
    "data_id": 71666415, 
    "sample_name": "BXD101", 
    "sample_name_2": "BXD101", 
    "se": 0.219203, 
    "value": 6.567
  }, 
  {
    "data_id": 71666415, 
    "sample_name": "BXD102", 
    "sample_name_2": "BXD102", 
    "se": 0.514774, 
    "value": 6.146
  }, 
  {
    "data_id": 71666415, 
    "sample_name": "BXD11", 
    "sample_name_2": "BXD11", 
    "se": 0.0919239, 
    "value": 5.736
  }, 
  {
    "data_id": 71666415, 
    "sample_name": "BXD12", 
    "sample_name_2": "BXD12", 
    "se": 0.00212132, 
    "value": 6.8985
  }, 
  {
    "data_id": 71666415, 
    "sample_name": "BXD14", 
    "sample_name_2": "BXD14", 
    "se": 0.639225, 
    "value": 6.282
  }, 
  {
    "data_id": 71666415, 
    "sample_name": "BXD24", 
    "sample_name_2": "BXD24", 
    "se": 0.296278, 
    "value": 6.9065
  }, 
  {
    "data_id": 71666415, 
    "sample_name": "BXD27", 
    "sample_name_2": "BXD27", 
    "se": 0.243952, 
    "value": 6.0025
  }, 
  {
    "data_id": 71666415, 
    "sample_name": "BXD29", 
    "sample_name_2": "BXD29", 
    "se": 0.234052, 
    "value": 5.5475
  }, 
  {
    "data_id": 71666415, 
    "sample_name": "BXD31", 
    "sample_name_2": "BXD31", 
    "se": 1.5224, 
    "value": 6.2615
  }, 
  {
    "data_id": 71666415, 
    "sample_name": "BXD32", 
    "sample_name_2": "BXD32", 
    "se": 0.0721249, 
    "value": 6.58
  }, 
  {
    "data_id": 71666415, 
    "sample_name": "BXD34", 
    "sample_name_2": "BXD34", 
    "se": 0.240529, 
    "value": 6.065
  }, 
  {
    "data_id": 71666415, 
    "sample_name": "BXD39", 
    "sample_name_2": "BXD39", 
    "se": 0.0318198, 
    "value": 6.6555
  }, 
  {
    "data_id": 71666415, 
    "sample_name": "BXD40", 
    "sample_name_2": "BXD40", 
    "se": 0.265872, 
    "value": 6.395
  }, 
  {
    "data_id": 71666415, 
    "sample_name": "BXD42", 
    "sample_name_2": "BXD42", 
    "se": 0.257387, 
    "value": 6.173
  }, 
  {
    "data_id": 71666415, 
    "sample_name": "BXD43", 
    "sample_name_2": "BXD43", 
    "se": 0.250312, 
    "value": 5.79233
  }, 
  {
    "data_id": 71666415, 
    "sample_name": "BXD44", 
    "sample_name_2": "BXD44", 
    "se": 0.267978, 
    "value": 6.1094
  }, 
  {
    "data_id": 71666415, 
    "sample_name": "BXD45", 
    "sample_name_2": "BXD45", 
    "se": 0.129401, 
    "value": 6.5045
  }, 
  {
    "data_id": 71666415, 
    "sample_name": "BXD48", 
    "sample_name_2": "BXD48", 
    "se": 0.0275772, 
    "value": 6.6765
  }, 
  {
    "data_id": 71666415, 
    "sample_name": "BXD49", 
    "sample_name_2": "BXD49", 
    "value": 6.326
  }, 
  {
    "data_id": 71666415, 
    "sample_name": "BXD50", 
    "sample_name_2": "BXD50", 
    "se": 0.111723, 
    "value": 6.202
  }, 
  {
    "data_id": 71666415, 
    "sample_name": "BXD56", 
    "sample_name_2": "BXD56", 
    "se": 0.238169, 
    "value": 6.605
  }, 
  {
    "data_id": 71666415, 
    "sample_name": "BXD60", 
    "sample_name_2": "BXD60", 
    "se": 0.65266, 
    "value": 6.4115
  }, 
  {
    "data_id": 71666415, 
    "sample_name": "BXD62", 
    "sample_name_2": "BXD62", 
    "se": 0.470226, 
    "value": 6.7275
  }, 
  {
    "data_id": 71666415, 
    "sample_name": "BXD63", 
    "sample_name_2": "BXD63", 
    "se": 0.212839, 
    "value": 5.8435
  }, 
  {
    "data_id": 71666415, 
    "sample_name": "BXD65", 
    "sample_name_2": "BXD65", 
    "se": 1.1243, 
    "value": 5.713
  }, 
  {
    "data_id": 71666415, 
    "sample_name": "BXD65a", 
    "sample_name_2": "BXD97", 
    "se": 0.0296985, 
    "value": 6.578
  }, 
  {
    "data_id": 71666415, 
    "sample_name": "BXD65b", 
    "sample_name_2": "BXD92", 
    "se": 0.277186, 
    "value": 6.391
  }, 
  {
    "data_id": 71666415, 
    "sample_name": "BXD68", 
    "sample_name_2": "BXD68", 
    "se": 0.127279, 
    "value": 6.459
  }, 
  {
    "data_id": 71666415, 
    "sample_name": "BXD69", 
    "sample_name_2": "BXD69", 
    "se": 0.225567, 
    "value": 6.3715
  }, 
  {
    "data_id": 71666415, 
    "sample_name": "BXD70", 
    "sample_name_2": "BXD70", 
    "se": 0.378302, 
    "value": 6.7965
  }, 
  {
    "data_id": 71666415, 
    "sample_name": "BXD71", 
    "sample_name_2": "BXD71", 
    "se": 0.0487904, 
    "value": 6.0425
  }, 
  {
    "data_id": 71666415, 
    "sample_name": "BXD73", 
    "sample_name_2": "BXD73", 
    "se": 0.242538, 
    "value": 6.5405
  }, 
  {
    "data_id": 71666415, 
    "sample_name": "BXD73a", 
    "sample_name_2": "BXD80", 
    "se": 1.18228, 
    "value": 5.971
  }, 
  {
    "data_id": 71666415, 
    "sample_name": "BXD73b", 
    "sample_name_2": "BXD103", 
    "se": 0.610233, 
    "value": 5.8465
  }, 
  {
    "data_id": 71666415, 
    "sample_name": "BXD75", 
    "sample_name_2": "BXD75", 
    "se": 0.807516, 
    "value": 6.185
  }, 
  {
    "data_id": 71666415, 
    "sample_name": "BXD79", 
    "sample_name_2": "BXD79", 
    "se": 0.235467, 
    "value": 6.9825
  }, 
  {
    "data_id": 71666415, 
    "sample_name": "BXD83", 
    "sample_name_2": "BXD83", 
    "se": 0.0127279, 
    "value": 6.822
  }, 
  {
    "data_id": 71666415, 
    "sample_name": "BXD84", 
    "sample_name_2": "BXD84", 
    "se": 0.280721, 
    "value": 6.3005
  }, 
  {
    "data_id": 71666415, 
    "sample_name": "BXD85", 
    "sample_name_2": "BXD85", 
    "se": 0.946109, 
    "value": 6.604
  }, 
  {
    "data_id": 71666415, 
    "sample_name": "BXD87", 
    "sample_name_2": "BXD87", 
    "se": 0.596798, 
    "value": 5.879
  }, 
  {
    "data_id": 71666415, 
    "sample_name": "BXD89", 
    "sample_name_2": "BXD89", 
    "se": 0.253851, 
    "value": 6.4765
  }, 
  {
    "data_id": 71666415, 
    "sample_name": "BXD90", 
    "sample_name_2": "BXD90", 
    "se": 0.38608, 
    "value": 6.89
  }, 
  {
    "data_id": 71666415, 
    "sample_name": "BXD95", 
    "sample_name_2": "BXD95", 
    "se": 0.225224, 
    "value": 6.685
  }, 
  {
    "data_id": 71666415, 
    "sample_name": "BXD99", 
    "sample_name_2": "BXD99", 
    "se": 0.511945, 
    "value": 6.68
  }, 
  {
    "data_id": 71666415, 
    "sample_name": "C57BL/6J", 
    "sample_name_2": "C57BL/6J", 
    "se": 0.111117, 
    "value": 6.77625
  }, 
  {
    "data_id": 71666415, 
    "sample_name": "D2B6F1", 
    "sample_name_2": "D2B6F1", 
    "se": 0.27365, 
    "value": 6.8025
  }, 
  {
    "data_id": 71666415, 
    "sample_name": "DBA/2J", 
    "sample_name_2": "DBA/2J", 
    "se": 0.440714, 
    "value": 6.18267
  }
]
