[
  {
    "data_id": 65741430, 
    "sample_name": "B6D2F1", 
    "sample_name_2": "B6D2F1", 
    "se": 0.013, 
    "value": 10.83
  }, 
  {
    "data_id": 65741430, 
    "sample_name": "BXD1", 
    "sample_name_2": "BXD1", 
    "se": 0.154, 
    "value": 10.867
  }, 
  {
    "data_id": 65741430, 
    "sample_name": "BXD100", 
    "sample_name_2": "BXD100", 
    "se": 0.278, 
    "value": 10.892
  }, 
  {
    "data_id": 65741430, 
    "sample_name": "BXD101", 
    "sample_name_2": "BXD101", 
    "se": 0.457, 
    "value": 10.427
  }, 
  {
    "data_id": 65741430, 
    "sample_name": "BXD102", 
    "sample_name_2": "BXD102", 
    "se": 0.035, 
    "value": 10.683
  }, 
  {
    "data_id": 65741430, 
    "sample_name": "BXD11", 
    "sample_name_2": "BXD11", 
    "se": 0.027, 
    "value": 10.681
  }, 
  {
    "data_id": 65741430, 
    "sample_name": "BXD12", 
    "sample_name_2": "BXD12", 
    "se": 0.032, 
    "value": 10.686
  }, 
  {
    "data_id": 65741430, 
    "sample_name": "BXD14", 
    "sample_name_2": "BXD14", 
    "se": 0.279, 
    "value": 10.892
  }, 
  {
    "data_id": 65741430, 
    "sample_name": "BXD24", 
    "sample_name_2": "BXD24", 
    "value": 10.855
  }, 
  {
    "data_id": 65741430, 
    "sample_name": "BXD27", 
    "sample_name_2": "BXD27", 
    "se": 0.11, 
    "value": 10.768
  }, 
  {
    "data_id": 65741430, 
    "sample_name": "BXD29", 
    "sample_name_2": "BXD29", 
    "se": 0.101, 
    "value": 10.812
  }, 
  {
    "data_id": 65741430, 
    "sample_name": "BXD31", 
    "sample_name_2": "BXD31", 
    "se": 0.021, 
    "value": 10.656
  }, 
  {
    "data_id": 65741430, 
    "sample_name": "BXD32", 
    "sample_name_2": "BXD32", 
    "se": 0.088, 
    "value": 10.724
  }, 
  {
    "data_id": 65741430, 
    "sample_name": "BXD34", 
    "sample_name_2": "BXD34", 
    "se": 0.149, 
    "value": 10.538
  }, 
  {
    "data_id": 65741430, 
    "sample_name": "BXD39", 
    "sample_name_2": "BXD39", 
    "se": 0.081, 
    "value": 10.802
  }, 
  {
    "data_id": 65741430, 
    "sample_name": "BXD40", 
    "sample_name_2": "BXD40", 
    "se": 0.227, 
    "value": 10.727
  }, 
  {
    "data_id": 65741430, 
    "sample_name": "BXD42", 
    "sample_name_2": "BXD42", 
    "se": 0.419, 
    "value": 10.461
  }, 
  {
    "data_id": 65741430, 
    "sample_name": "BXD43", 
    "sample_name_2": "BXD43", 
    "se": 0.227, 
    "value": 10.549
  }, 
  {
    "data_id": 65741430, 
    "sample_name": "BXD44", 
    "sample_name_2": "BXD44", 
    "se": 0.099, 
    "value": 10.682
  }, 
  {
    "data_id": 65741430, 
    "sample_name": "BXD45", 
    "sample_name_2": "BXD45", 
    "se": 0.03, 
    "value": 10.702
  }, 
  {
    "data_id": 65741430, 
    "sample_name": "BXD48", 
    "sample_name_2": "BXD48", 
    "se": 0.07, 
    "value": 10.568
  }, 
  {
    "data_id": 65741430, 
    "sample_name": "BXD49", 
    "sample_name_2": "BXD49", 
    "value": 10.617
  }, 
  {
    "data_id": 65741430, 
    "sample_name": "BXD50", 
    "sample_name_2": "BXD50", 
    "se": 0.139, 
    "value": 10.443
  }, 
  {
    "data_id": 65741430, 
    "sample_name": "BXD56", 
    "sample_name_2": "BXD56", 
    "se": 0.121, 
    "value": 10.653
  }, 
  {
    "data_id": 65741430, 
    "sample_name": "BXD60", 
    "sample_name_2": "BXD60", 
    "se": 0.134, 
    "value": 10.918
  }, 
  {
    "data_id": 65741430, 
    "sample_name": "BXD62", 
    "sample_name_2": "BXD62", 
    "se": 0.075, 
    "value": 10.91
  }, 
  {
    "data_id": 65741430, 
    "sample_name": "BXD63", 
    "sample_name_2": "BXD63", 
    "se": 0.005, 
    "value": 10.605
  }, 
  {
    "data_id": 65741430, 
    "sample_name": "BXD65", 
    "sample_name_2": "BXD65", 
    "se": 0.399, 
    "value": 10.585
  }, 
  {
    "data_id": 65741430, 
    "sample_name": "BXD65a", 
    "sample_name_2": "BXD97", 
    "se": 0.332, 
    "value": 10.939
  }, 
  {
    "data_id": 65741430, 
    "sample_name": "BXD65b", 
    "sample_name_2": "BXD92", 
    "se": 0.061, 
    "value": 10.632
  }, 
  {
    "data_id": 65741430, 
    "sample_name": "BXD68", 
    "sample_name_2": "BXD68", 
    "se": 0.112, 
    "value": 10.864
  }, 
  {
    "data_id": 65741430, 
    "sample_name": "BXD69", 
    "sample_name_2": "BXD69", 
    "se": 0.105, 
    "value": 10.707
  }, 
  {
    "data_id": 65741430, 
    "sample_name": "BXD70", 
    "sample_name_2": "BXD70", 
    "se": 0.122, 
    "value": 10.83
  }, 
  {
    "data_id": 65741430, 
    "sample_name": "BXD71", 
    "sample_name_2": "BXD71", 
    "se": 0.337, 
    "value": 10.668
  }, 
  {
    "data_id": 65741430, 
    "sample_name": "BXD73", 
    "sample_name_2": "BXD73", 
    "se": 0.002, 
    "value": 10.662
  }, 
  {
    "data_id": 65741430, 
    "sample_name": "BXD73a", 
    "sample_name_2": "BXD80", 
    "se": 0.207, 
    "value": 10.843
  }, 
  {
    "data_id": 65741430, 
    "sample_name": "BXD73b", 
    "sample_name_2": "BXD103", 
    "se": 0.078, 
    "value": 10.988
  }, 
  {
    "data_id": 65741430, 
    "sample_name": "BXD75", 
    "sample_name_2": "BXD75", 
    "se": 0.133, 
    "value": 10.985
  }, 
  {
    "data_id": 65741430, 
    "sample_name": "BXD79", 
    "sample_name_2": "BXD79", 
    "se": 0.314, 
    "value": 10.808
  }, 
  {
    "data_id": 65741430, 
    "sample_name": "BXD83", 
    "sample_name_2": "BXD83", 
    "se": 0.016, 
    "value": 10.583
  }, 
  {
    "data_id": 65741430, 
    "sample_name": "BXD84", 
    "sample_name_2": "BXD84", 
    "se": 0.011, 
    "value": 10.766
  }, 
  {
    "data_id": 65741430, 
    "sample_name": "BXD85", 
    "sample_name_2": "BXD85", 
    "se": 0.151, 
    "value": 10.498
  }, 
  {
    "data_id": 65741430, 
    "sample_name": "BXD87", 
    "sample_name_2": "BXD87", 
    "se": 0.259, 
    "value": 10.62
  }, 
  {
    "data_id": 65741430, 
    "sample_name": "BXD89", 
    "sample_name_2": "BXD89", 
    "se": 0.178, 
    "value": 10.916
  }, 
  {
    "data_id": 65741430, 
    "sample_name": "BXD90", 
    "sample_name_2": "BXD90", 
    "se": 0.042, 
    "value": 10.588
  }, 
  {
    "data_id": 65741430, 
    "sample_name": "BXD95", 
    "sample_name_2": "BXD95", 
    "se": 0.203, 
    "value": 10.801
  }, 
  {
    "data_id": 65741430, 
    "sample_name": "BXD99", 
    "sample_name_2": "BXD99", 
    "se": 0.066, 
    "value": 10.602
  }, 
  {
    "data_id": 65741430, 
    "sample_name": "C57BL/6J", 
    "sample_name_2": "C57BL/6J", 
    "se": 0.168, 
    "value": 10.62
  }, 
  {
    "data_id": 65741430, 
    "sample_name": "D2B6F1", 
    "sample_name_2": "D2B6F1", 
    "se": 0.246, 
    "value": 11.017
  }, 
  {
    "data_id": 65741430, 
    "sample_name": "DBA/2J", 
    "sample_name_2": "DBA/2J", 
    "se": 0.07, 
    "value": 10.751
  }
]
