[
  {
    "data_id": 82791340, 
    "sample_name": "B6D2F1", 
    "sample_name_2": "B6D2F1", 
    "se": 0.052176, 
    "value": 14.232
  }, 
  {
    "data_id": 82791340, 
    "sample_name": "BXD100", 
    "sample_name_2": "BXD100", 
    "se": 0.090902, 
    "value": 14.296
  }, 
  {
    "data_id": 82791340, 
    "sample_name": "BXD101", 
    "sample_name_2": "BXD101", 
    "se": 0.09594, 
    "value": 14.346
  }, 
  {
    "data_id": 82791340, 
    "sample_name": "BXD102", 
    "sample_name_2": "BXD102", 
    "se": 0.058449, 
    "value": 14.293
  }, 
  {
    "data_id": 82791340, 
    "sample_name": "BXD13", 
    "sample_name_2": "BXD13", 
    "value": 14.609
  }, 
  {
    "data_id": 82791340, 
    "sample_name": "BXD24", 
    "sample_name_2": "BXD24", 
    "se": 0.08364, 
    "value": 14.447
  }, 
  {
    "data_id": 82791340, 
    "sample_name": "BXD27", 
    "sample_name_2": "BXD27", 
    "se": 0.112036, 
    "value": 14.297
  }, 
  {
    "data_id": 82791340, 
    "sample_name": "BXD29", 
    "sample_name_2": "BXD29", 
    "se": 0.079152, 
    "value": 14.356
  }, 
  {
    "data_id": 82791340, 
    "sample_name": "BXD32", 
    "sample_name_2": "BXD32", 
    "se": 0.057434, 
    "value": 14.215
  }, 
  {
    "data_id": 82791340, 
    "sample_name": "BXD34", 
    "sample_name_2": "BXD34", 
    "se": 0.067388, 
    "value": 14.179
  }, 
  {
    "data_id": 82791340, 
    "sample_name": "BXD39", 
    "sample_name_2": "BXD39", 
    "se": 0.072133, 
    "value": 14.34
  }, 
  {
    "data_id": 82791340, 
    "sample_name": "BXD40", 
    "sample_name_2": "BXD40", 
    "se": 0.090098, 
    "value": 14.553
  }, 
  {
    "data_id": 82791340, 
    "sample_name": "BXD43", 
    "sample_name_2": "BXD43", 
    "se": 0.149661, 
    "value": 14.234
  }, 
  {
    "data_id": 82791340, 
    "sample_name": "BXD44", 
    "sample_name_2": "BXD44", 
    "se": 0.06476, 
    "value": 14.325
  }, 
  {
    "data_id": 82791340, 
    "sample_name": "BXD45", 
    "sample_name_2": "BXD45", 
    "se": 0.045419, 
    "value": 14.281
  }, 
  {
    "data_id": 82791340, 
    "sample_name": "BXD48", 
    "sample_name_2": "BXD48", 
    "se": 0.076665, 
    "value": 14.287
  }, 
  {
    "data_id": 82791340, 
    "sample_name": "BXD48a", 
    "sample_name_2": "BXD96", 
    "se": 0.137194, 
    "value": 14.14
  }, 
  {
    "data_id": 82791340, 
    "sample_name": "BXD49", 
    "sample_name_2": "BXD49", 
    "se": 0.191626, 
    "value": 14.331
  }, 
  {
    "data_id": 82791340, 
    "sample_name": "BXD50", 
    "sample_name_2": "BXD50", 
    "se": 0.124218, 
    "value": 14.447
  }, 
  {
    "data_id": 82791340, 
    "sample_name": "BXD51", 
    "sample_name_2": "BXD51", 
    "se": 0.099115, 
    "value": 14.228
  }, 
  {
    "data_id": 82791340, 
    "sample_name": "BXD53", 
    "sample_name_2": "BXD53", 
    "se": 0.013802, 
    "value": 14.231
  }, 
  {
    "data_id": 82791340, 
    "sample_name": "BXD55", 
    "sample_name_2": "BXD55", 
    "value": 14.089
  }, 
  {
    "data_id": 82791340, 
    "sample_name": "BXD56", 
    "sample_name_2": "BXD56", 
    "value": 14.374
  }, 
  {
    "data_id": 82791340, 
    "sample_name": "BXD60", 
    "sample_name_2": "BXD60", 
    "se": 0.0711, 
    "value": 14.119
  }, 
  {
    "data_id": 82791340, 
    "sample_name": "BXD61", 
    "sample_name_2": "BXD61", 
    "se": 0.067445, 
    "value": 14.207
  }, 
  {
    "data_id": 82791340, 
    "sample_name": "BXD62", 
    "sample_name_2": "BXD62", 
    "se": 0.049542, 
    "value": 14.303
  }, 
  {
    "data_id": 82791340, 
    "sample_name": "BXD63", 
    "sample_name_2": "BXD63", 
    "se": 0.069224, 
    "value": 14.166
  }, 
  {
    "data_id": 82791340, 
    "sample_name": "BXD64", 
    "sample_name_2": "BXD64", 
    "se": 0.281632, 
    "value": 14.147
  }, 
  {
    "data_id": 82791340, 
    "sample_name": "BXD65", 
    "sample_name_2": "BXD65", 
    "se": 0.042285, 
    "value": 14.304
  }, 
  {
    "data_id": 82791340, 
    "sample_name": "BXD65b", 
    "sample_name_2": "BXD92", 
    "se": 0.09932, 
    "value": 14.399
  }, 
  {
    "data_id": 82791340, 
    "sample_name": "BXD66", 
    "sample_name_2": "BXD66", 
    "se": 0.055972, 
    "value": 14.171
  }, 
  {
    "data_id": 82791340, 
    "sample_name": "BXD67", 
    "sample_name_2": "BXD67", 
    "se": 0.093338, 
    "value": 14.352
  }, 
  {
    "data_id": 82791340, 
    "sample_name": "BXD68", 
    "sample_name_2": "BXD68", 
    "se": 0.007778, 
    "value": 14.049
  }, 
  {
    "data_id": 82791340, 
    "sample_name": "BXD69", 
    "sample_name_2": "BXD69", 
    "se": 0.113024, 
    "value": 14.221
  }, 
  {
    "data_id": 82791340, 
    "sample_name": "BXD70", 
    "sample_name_2": "BXD70", 
    "se": 0.12382, 
    "value": 14.222
  }, 
  {
    "data_id": 82791340, 
    "sample_name": "BXD73", 
    "sample_name_2": "BXD73", 
    "se": 0.101591, 
    "value": 14.027
  }, 
  {
    "data_id": 82791340, 
    "sample_name": "BXD73b", 
    "sample_name_2": "BXD103", 
    "se": 0.076294, 
    "value": 14.096
  }, 
  {
    "data_id": 82791340, 
    "sample_name": "BXD74", 
    "sample_name_2": "BXD74", 
    "value": 14.255
  }, 
  {
    "data_id": 82791340, 
    "sample_name": "BXD75", 
    "sample_name_2": "BXD75", 
    "se": 0.000707, 
    "value": 14.104
  }, 
  {
    "data_id": 82791340, 
    "sample_name": "BXD77", 
    "sample_name_2": "BXD77", 
    "se": 0.105063, 
    "value": 14.172
  }, 
  {
    "data_id": 82791340, 
    "sample_name": "BXD79", 
    "sample_name_2": "BXD79", 
    "se": 0.134307, 
    "value": 14.299
  }, 
  {
    "data_id": 82791340, 
    "sample_name": "BXD81", 
    "sample_name_2": "BXD81", 
    "se": 0.409415, 
    "value": 14.234
  }, 
  {
    "data_id": 82791340, 
    "sample_name": "BXD83", 
    "sample_name_2": "BXD83", 
    "value": 14.41
  }, 
  {
    "data_id": 82791340, 
    "sample_name": "BXD84", 
    "sample_name_2": "BXD84", 
    "se": 0.02687, 
    "value": 14.03
  }, 
  {
    "data_id": 82791340, 
    "sample_name": "BXD86", 
    "sample_name_2": "BXD86", 
    "se": 0.055714, 
    "value": 14.08
  }, 
  {
    "data_id": 82791340, 
    "sample_name": "BXD87", 
    "sample_name_2": "BXD87", 
    "se": 0.142423, 
    "value": 14.204
  }, 
  {
    "data_id": 82791340, 
    "sample_name": "BXD88", 
    "sample_name_2": "BXD88", 
    "value": 14.395
  }, 
  {
    "data_id": 82791340, 
    "sample_name": "BXD89", 
    "sample_name_2": "BXD89", 
    "se": 0.08193, 
    "value": 14.235
  }, 
  {
    "data_id": 82791340, 
    "sample_name": "BXD9", 
    "sample_name_2": "BXD9", 
    "se": 0.086403, 
    "value": 14.133
  }, 
  {
    "data_id": 82791340, 
    "sample_name": "BXD90", 
    "sample_name_2": "BXD90", 
    "se": 0.131828, 
    "value": 14.288
  }, 
  {
    "data_id": 82791340, 
    "sample_name": "BXD91", 
    "sample_name_2": "BXD91", 
    "se": 0.009192, 
    "value": 14.212
  }, 
  {
    "data_id": 82791340, 
    "sample_name": "BXD95", 
    "sample_name_2": "BXD95", 
    "se": 0.02629, 
    "value": 14.26
  }, 
  {
    "data_id": 82791340, 
    "sample_name": "BXD98", 
    "sample_name_2": "BXD98", 
    "se": 0.062122, 
    "value": 14.167
  }, 
  {
    "data_id": 82791340, 
    "sample_name": "BXD99", 
    "sample_name_2": "BXD99", 
    "se": 0.019092, 
    "value": 14.331
  }, 
  {
    "data_id": 82791340, 
    "sample_name": "C57BL/6J", 
    "sample_name_2": "C57BL/6J", 
    "se": 0.078439, 
    "value": 14.244
  }, 
  {
    "data_id": 82791340, 
    "sample_name": "D2B6F1", 
    "sample_name_2": "D2B6F1", 
    "se": 0.078298, 
    "value": 14.195
  }, 
  {
    "data_id": 82791340, 
    "sample_name": "DBA/2J", 
    "sample_name_2": "DBA/2J", 
    "se": 0.040304, 
    "value": 14.359
  }
]
