[
  {
    "data_id": 71775324, 
    "sample_name": "B6D2F1", 
    "sample_name_2": "B6D2F1", 
    "se": 0.325269, 
    "value": 6.519
  }, 
  {
    "data_id": 71775324, 
    "sample_name": "BXD1", 
    "sample_name_2": "BXD1", 
    "se": 0.0360624, 
    "value": 5.6895
  }, 
  {
    "data_id": 71775324, 
    "sample_name": "BXD100", 
    "sample_name_2": "BXD100", 
    "se": 0.748826, 
    "value": 6.1125
  }, 
  {
    "data_id": 71775324, 
    "sample_name": "BXD101", 
    "sample_name_2": "BXD101", 
    "se": 0.00282843, 
    "value": 6.177
  }, 
  {
    "data_id": 71775324, 
    "sample_name": "BXD102", 
    "sample_name_2": "BXD102", 
    "se": 0.280721, 
    "value": 6.1655
  }, 
  {
    "data_id": 71775324, 
    "sample_name": "BXD11", 
    "sample_name_2": "BXD11", 
    "se": 0.25668, 
    "value": 6.4355
  }, 
  {
    "data_id": 71775324, 
    "sample_name": "BXD12", 
    "sample_name_2": "BXD12", 
    "se": 0.323148, 
    "value": 6.2465
  }, 
  {
    "data_id": 71775324, 
    "sample_name": "BXD14", 
    "sample_name_2": "BXD14", 
    "se": 0.259508, 
    "value": 6.2635
  }, 
  {
    "data_id": 71775324, 
    "sample_name": "BXD24", 
    "sample_name_2": "BXD24", 
    "se": 0.252437, 
    "value": 5.9085
  }, 
  {
    "data_id": 71775324, 
    "sample_name": "BXD27", 
    "sample_name_2": "BXD27", 
    "se": 0.19799, 
    "value": 5.913
  }, 
  {
    "data_id": 71775324, 
    "sample_name": "BXD29", 
    "sample_name_2": "BXD29", 
    "se": 0.125865, 
    "value": 6.165
  }, 
  {
    "data_id": 71775324, 
    "sample_name": "BXD31", 
    "sample_name_2": "BXD31", 
    "se": 0.575585, 
    "value": 6.265
  }, 
  {
    "data_id": 71775324, 
    "sample_name": "BXD32", 
    "sample_name_2": "BXD32", 
    "se": 0.335876, 
    "value": 6.2925
  }, 
  {
    "data_id": 71775324, 
    "sample_name": "BXD34", 
    "sample_name_2": "BXD34", 
    "se": 0.440199, 
    "value": 6.22167
  }, 
  {
    "data_id": 71775324, 
    "sample_name": "BXD39", 
    "sample_name_2": "BXD39", 
    "se": 0.281428, 
    "value": 6.285
  }, 
  {
    "data_id": 71775324, 
    "sample_name": "BXD40", 
    "sample_name_2": "BXD40", 
    "se": 0.50346, 
    "value": 5.854
  }, 
  {
    "data_id": 71775324, 
    "sample_name": "BXD42", 
    "sample_name_2": "BXD42", 
    "se": 0.059397, 
    "value": 6.06
  }, 
  {
    "data_id": 71775324, 
    "sample_name": "BXD43", 
    "sample_name_2": "BXD43", 
    "se": 0.150061, 
    "value": 6.29433
  }, 
  {
    "data_id": 71775324, 
    "sample_name": "BXD44", 
    "sample_name_2": "BXD44", 
    "se": 0.265231, 
    "value": 6.3912
  }, 
  {
    "data_id": 71775324, 
    "sample_name": "BXD45", 
    "sample_name_2": "BXD45", 
    "se": 0.177484, 
    "value": 6.1345
  }, 
  {
    "data_id": 71775324, 
    "sample_name": "BXD48", 
    "sample_name_2": "BXD48", 
    "se": 0.758018, 
    "value": 6.316
  }, 
  {
    "data_id": 71775324, 
    "sample_name": "BXD49", 
    "sample_name_2": "BXD49", 
    "value": 6.882
  }, 
  {
    "data_id": 71775324, 
    "sample_name": "BXD50", 
    "sample_name_2": "BXD50", 
    "se": 0.666802, 
    "value": 5.8915
  }, 
  {
    "data_id": 71775324, 
    "sample_name": "BXD56", 
    "sample_name_2": "BXD56", 
    "se": 0.30013, 
    "value": 6.306
  }, 
  {
    "data_id": 71775324, 
    "sample_name": "BXD60", 
    "sample_name_2": "BXD60", 
    "se": 0.0403051, 
    "value": 5.8195
  }, 
  {
    "data_id": 71775324, 
    "sample_name": "BXD62", 
    "sample_name_2": "BXD62", 
    "se": 0.64276, 
    "value": 6.8135
  }, 
  {
    "data_id": 71775324, 
    "sample_name": "BXD63", 
    "sample_name_2": "BXD63", 
    "se": 0.0360624, 
    "value": 5.5425
  }, 
  {
    "data_id": 71775324, 
    "sample_name": "BXD65", 
    "sample_name_2": "BXD65", 
    "se": 0.214253, 
    "value": 5.9285
  }, 
  {
    "data_id": 71775324, 
    "sample_name": "BXD65a", 
    "sample_name_2": "BXD97", 
    "se": 0.205768, 
    "value": 5.9165
  }, 
  {
    "data_id": 71775324, 
    "sample_name": "BXD65b", 
    "sample_name_2": "BXD92", 
    "se": 0.187383, 
    "value": 6.1755
  }, 
  {
    "data_id": 71775324, 
    "sample_name": "BXD68", 
    "sample_name_2": "BXD68", 
    "se": 0.147785, 
    "value": 5.9115
  }, 
  {
    "data_id": 71775324, 
    "sample_name": "BXD69", 
    "sample_name_2": "BXD69", 
    "se": 0.205061, 
    "value": 6.643
  }, 
  {
    "data_id": 71775324, 
    "sample_name": "BXD70", 
    "sample_name_2": "BXD70", 
    "se": 0.232638, 
    "value": 5.9335
  }, 
  {
    "data_id": 71775324, 
    "sample_name": "BXD71", 
    "sample_name_2": "BXD71", 
    "se": 0.506996, 
    "value": 5.6205
  }, 
  {
    "data_id": 71775324, 
    "sample_name": "BXD73", 
    "sample_name_2": "BXD73", 
    "se": 0.360624, 
    "value": 6.411
  }, 
  {
    "data_id": 71775324, 
    "sample_name": "BXD73a", 
    "sample_name_2": "BXD80", 
    "se": 0.836507, 
    "value": 6.7035
  }, 
  {
    "data_id": 71775324, 
    "sample_name": "BXD73b", 
    "sample_name_2": "BXD103", 
    "se": 0.401637, 
    "value": 5.89
  }, 
  {
    "data_id": 71775324, 
    "sample_name": "BXD75", 
    "sample_name_2": "BXD75", 
    "se": 0.0579828, 
    "value": 6.298
  }, 
  {
    "data_id": 71775324, 
    "sample_name": "BXD79", 
    "sample_name_2": "BXD79", 
    "se": 0.94328, 
    "value": 5.923
  }, 
  {
    "data_id": 71775324, 
    "sample_name": "BXD83", 
    "sample_name_2": "BXD83", 
    "se": 0.157685, 
    "value": 6.0875
  }, 
  {
    "data_id": 71775324, 
    "sample_name": "BXD84", 
    "sample_name_2": "BXD84", 
    "se": 0.145664, 
    "value": 5.991
  }, 
  {
    "data_id": 71775324, 
    "sample_name": "BXD85", 
    "sample_name_2": "BXD85", 
    "se": 0.348604, 
    "value": 6.1735
  }, 
  {
    "data_id": 71775324, 
    "sample_name": "BXD87", 
    "sample_name_2": "BXD87", 
    "se": 0.30547, 
    "value": 6.242
  }, 
  {
    "data_id": 71775324, 
    "sample_name": "BXD89", 
    "sample_name_2": "BXD89", 
    "se": 0.373352, 
    "value": 5.629
  }, 
  {
    "data_id": 71775324, 
    "sample_name": "BXD90", 
    "sample_name_2": "BXD90", 
    "se": 0.147785, 
    "value": 5.6895
  }, 
  {
    "data_id": 71775324, 
    "sample_name": "BXD95", 
    "sample_name_2": "BXD95", 
    "se": 0.444142, 
    "value": 5.965
  }, 
  {
    "data_id": 71775324, 
    "sample_name": "BXD99", 
    "sample_name_2": "BXD99", 
    "se": 0.441235, 
    "value": 5.747
  }, 
  {
    "data_id": 71775324, 
    "sample_name": "C57BL/6J", 
    "sample_name_2": "C57BL/6J", 
    "se": 0.386363, 
    "value": 5.834
  }, 
  {
    "data_id": 71775324, 
    "sample_name": "D2B6F1", 
    "sample_name_2": "D2B6F1", 
    "se": 1.16955, 
    "value": 6.205
  }, 
  {
    "data_id": 71775324, 
    "sample_name": "DBA/2J", 
    "sample_name_2": "DBA/2J", 
    "se": 0.159926, 
    "value": 5.52933
  }
]
