[
  {
    "data_id": 40033989, 
    "sample_name": "BXD1", 
    "sample_name_2": "BXD1", 
    "value": 7.11559
  }, 
  {
    "data_id": 40033989, 
    "sample_name": "BXD11", 
    "sample_name_2": "BXD11", 
    "value": 6.92167
  }, 
  {
    "data_id": 40033989, 
    "sample_name": "BXD12", 
    "sample_name_2": "BXD12", 
    "value": 7.20026
  }, 
  {
    "data_id": 40033989, 
    "sample_name": "BXD13", 
    "sample_name_2": "BXD13", 
    "value": 7.31243
  }, 
  {
    "data_id": 40033989, 
    "sample_name": "BXD14", 
    "sample_name_2": "BXD14", 
    "value": 6.84888
  }, 
  {
    "data_id": 40033989, 
    "sample_name": "BXD15", 
    "sample_name_2": "BXD15", 
    "value": 7.08791
  }, 
  {
    "data_id": 40033989, 
    "sample_name": "BXD16", 
    "sample_name_2": "BXD16", 
    "value": 6.93128
  }, 
  {
    "data_id": 40033989, 
    "sample_name": "BXD18", 
    "sample_name_2": "BXD18", 
    "value": 6.60631
  }, 
  {
    "data_id": 40033989, 
    "sample_name": "BXD2", 
    "sample_name_2": "BXD2", 
    "value": 6.67223
  }, 
  {
    "data_id": 40033989, 
    "sample_name": "BXD21", 
    "sample_name_2": "BXD21", 
    "value": 6.89522
  }, 
  {
    "data_id": 40033989, 
    "sample_name": "BXD23", 
    "sample_name_2": "BXD23", 
    "value": 7.03681
  }, 
  {
    "data_id": 40033989, 
    "sample_name": "BXD27", 
    "sample_name_2": "BXD27", 
    "value": 6.84282
  }, 
  {
    "data_id": 40033989, 
    "sample_name": "BXD28", 
    "sample_name_2": "BXD28", 
    "value": 6.98207
  }, 
  {
    "data_id": 40033989, 
    "sample_name": "BXD29", 
    "sample_name_2": "BXD29", 
    "value": 6.95711
  }, 
  {
    "data_id": 40033989, 
    "sample_name": "BXD31", 
    "sample_name_2": "BXD31", 
    "value": 6.58716
  }, 
  {
    "data_id": 40033989, 
    "sample_name": "BXD32", 
    "sample_name_2": "BXD32", 
    "value": 6.72633
  }, 
  {
    "data_id": 40033989, 
    "sample_name": "BXD33", 
    "sample_name_2": "BXD33", 
    "value": 6.77529
  }, 
  {
    "data_id": 40033989, 
    "sample_name": "BXD34", 
    "sample_name_2": "BXD34", 
    "value": 6.86377
  }, 
  {
    "data_id": 40033989, 
    "sample_name": "BXD36", 
    "sample_name_2": "BXD36", 
    "value": 7.08069
  }, 
  {
    "data_id": 40033989, 
    "sample_name": "BXD40", 
    "sample_name_2": "BXD40", 
    "value": 6.98156
  }, 
  {
    "data_id": 40033989, 
    "sample_name": "BXD42", 
    "sample_name_2": "BXD42", 
    "value": 6.98232
  }, 
  {
    "data_id": 40033989, 
    "sample_name": "BXD6", 
    "sample_name_2": "BXD6", 
    "value": 7.03195
  }, 
  {
    "data_id": 40033989, 
    "sample_name": "BXD8", 
    "sample_name_2": "BXD8", 
    "value": 7.06373
  }
]
