[
  {
    "data_id": 59325004, 
    "sample_name": "B6D2F1", 
    "sample_name_2": "B6D2F1", 
    "se": 0.128, 
    "value": 16.119
  }, 
  {
    "data_id": 59325004, 
    "sample_name": "BXD12", 
    "sample_name_2": "BXD12", 
    "se": 0.274, 
    "value": 15.817
  }, 
  {
    "data_id": 59325004, 
    "sample_name": "BXD14", 
    "sample_name_2": "BXD14", 
    "value": 15.998
  }, 
  {
    "data_id": 59325004, 
    "sample_name": "BXD15", 
    "sample_name_2": "BXD15", 
    "se": 0.43, 
    "value": 15.807
  }, 
  {
    "data_id": 59325004, 
    "sample_name": "BXD19", 
    "sample_name_2": "BXD19", 
    "value": 16.061
  }, 
  {
    "data_id": 59325004, 
    "sample_name": "BXD20", 
    "sample_name_2": "BXD20", 
    "se": 0.107, 
    "value": 16.17
  }, 
  {
    "data_id": 59325004, 
    "sample_name": "BXD21", 
    "sample_name_2": "BXD21", 
    "se": 0.311, 
    "value": 16.025
  }, 
  {
    "data_id": 59325004, 
    "sample_name": "BXD27", 
    "sample_name_2": "BXD27", 
    "se": 0.095, 
    "value": 15.904
  }, 
  {
    "data_id": 59325004, 
    "sample_name": "BXD32", 
    "sample_name_2": "BXD32", 
    "se": 0.123, 
    "value": 16.005
  }, 
  {
    "data_id": 59325004, 
    "sample_name": "BXD33", 
    "sample_name_2": "BXD33", 
    "se": 0.12, 
    "value": 16.084
  }, 
  {
    "data_id": 59325004, 
    "sample_name": "BXD34", 
    "sample_name_2": "BXD34", 
    "se": 0.035, 
    "value": 15.946
  }, 
  {
    "data_id": 59325004, 
    "sample_name": "BXD38", 
    "sample_name_2": "BXD38", 
    "se": 0.117, 
    "value": 15.703
  }, 
  {
    "data_id": 59325004, 
    "sample_name": "BXD39", 
    "sample_name_2": "BXD39", 
    "se": 0.143, 
    "value": 15.863
  }, 
  {
    "data_id": 59325004, 
    "sample_name": "BXD40", 
    "sample_name_2": "BXD40", 
    "se": 0.217, 
    "value": 15.846
  }, 
  {
    "data_id": 59325004, 
    "sample_name": "BXD42", 
    "sample_name_2": "BXD42", 
    "se": 0.125, 
    "value": 15.834
  }, 
  {
    "data_id": 59325004, 
    "sample_name": "BXD6", 
    "sample_name_2": "BXD6", 
    "se": 0.151, 
    "value": 16.131
  }
]
