[
  {
    "data_id": 71606570, 
    "sample_name": "B6D2F1", 
    "sample_name_2": "B6D2F1", 
    "se": 0.419314, 
    "value": 7.9505
  }, 
  {
    "data_id": 71606570, 
    "sample_name": "BXD1", 
    "sample_name_2": "BXD1", 
    "se": 0.140007, 
    "value": 8.192
  }, 
  {
    "data_id": 71606570, 
    "sample_name": "BXD100", 
    "sample_name_2": "BXD100", 
    "se": 0.0551543, 
    "value": 7.83
  }, 
  {
    "data_id": 71606570, 
    "sample_name": "BXD101", 
    "sample_name_2": "BXD101", 
    "se": 0.0381838, 
    "value": 7.733
  }, 
  {
    "data_id": 71606570, 
    "sample_name": "BXD102", 
    "sample_name_2": "BXD102", 
    "se": 0.175362, 
    "value": 7.613
  }, 
  {
    "data_id": 71606570, 
    "sample_name": "BXD11", 
    "sample_name_2": "BXD11", 
    "se": 0.0890955, 
    "value": 7.686
  }, 
  {
    "data_id": 71606570, 
    "sample_name": "BXD12", 
    "sample_name_2": "BXD12", 
    "se": 0.0502046, 
    "value": 7.8685
  }, 
  {
    "data_id": 71606570, 
    "sample_name": "BXD14", 
    "sample_name_2": "BXD14", 
    "se": 0.796202, 
    "value": 7.638
  }, 
  {
    "data_id": 71606570, 
    "sample_name": "BXD24", 
    "sample_name_2": "BXD24", 
    "se": 0.158392, 
    "value": 8.455
  }, 
  {
    "data_id": 71606570, 
    "sample_name": "BXD27", 
    "sample_name_2": "BXD27", 
    "se": 0.62084, 
    "value": 8.05
  }, 
  {
    "data_id": 71606570, 
    "sample_name": "BXD29", 
    "sample_name_2": "BXD29", 
    "se": 0.511238, 
    "value": 7.7825
  }, 
  {
    "data_id": 71606570, 
    "sample_name": "BXD31", 
    "sample_name_2": "BXD31", 
    "se": 0.67953, 
    "value": 8.2145
  }, 
  {
    "data_id": 71606570, 
    "sample_name": "BXD32", 
    "sample_name_2": "BXD32", 
    "se": 0.227688, 
    "value": 8.305
  }, 
  {
    "data_id": 71606570, 
    "sample_name": "BXD34", 
    "sample_name_2": "BXD34", 
    "se": 0.07678, 
    "value": 8.29833
  }, 
  {
    "data_id": 71606570, 
    "sample_name": "BXD39", 
    "sample_name_2": "BXD39", 
    "se": 0.227688, 
    "value": 8.079
  }, 
  {
    "data_id": 71606570, 
    "sample_name": "BXD40", 
    "sample_name_2": "BXD40", 
    "se": 0.371938, 
    "value": 7.863
  }, 
  {
    "data_id": 71606570, 
    "sample_name": "BXD42", 
    "sample_name_2": "BXD42", 
    "se": 0.00848528, 
    "value": 8.43
  }, 
  {
    "data_id": 71606570, 
    "sample_name": "BXD43", 
    "sample_name_2": "BXD43", 
    "se": 0.202239, 
    "value": 7.85733
  }, 
  {
    "data_id": 71606570, 
    "sample_name": "BXD44", 
    "sample_name_2": "BXD44", 
    "se": 0.191482, 
    "value": 7.7132
  }, 
  {
    "data_id": 71606570, 
    "sample_name": "BXD45", 
    "sample_name_2": "BXD45", 
    "se": 0.181019, 
    "value": 7.896
  }, 
  {
    "data_id": 71606570, 
    "sample_name": "BXD48", 
    "sample_name_2": "BXD48", 
    "se": 0.00353553, 
    "value": 8.0665
  }, 
  {
    "data_id": 71606570, 
    "sample_name": "BXD49", 
    "sample_name_2": "BXD49", 
    "value": 7.808
  }, 
  {
    "data_id": 71606570, 
    "sample_name": "BXD50", 
    "sample_name_2": "BXD50", 
    "se": 0.414365, 
    "value": 8.275
  }, 
  {
    "data_id": 71606570, 
    "sample_name": "BXD56", 
    "sample_name_2": "BXD56", 
    "se": 0.0955885, 
    "value": 8.00267
  }, 
  {
    "data_id": 71606570, 
    "sample_name": "BXD60", 
    "sample_name_2": "BXD60", 
    "se": 0.0431335, 
    "value": 7.8965
  }, 
  {
    "data_id": 71606570, 
    "sample_name": "BXD62", 
    "sample_name_2": "BXD62", 
    "se": 0.27365, 
    "value": 7.8895
  }, 
  {
    "data_id": 71606570, 
    "sample_name": "BXD63", 
    "sample_name_2": "BXD63", 
    "se": 0.299106, 
    "value": 7.8825
  }, 
  {
    "data_id": 71606570, 
    "sample_name": "BXD65", 
    "sample_name_2": "BXD65", 
    "se": 0.153442, 
    "value": 7.9985
  }, 
  {
    "data_id": 71606570, 
    "sample_name": "BXD65a", 
    "sample_name_2": "BXD97", 
    "se": 0.00636396, 
    "value": 8.0335
  }, 
  {
    "data_id": 71606570, 
    "sample_name": "BXD65b", 
    "sample_name_2": "BXD92", 
    "se": 0.277893, 
    "value": 8.2935
  }, 
  {
    "data_id": 71606570, 
    "sample_name": "BXD68", 
    "sample_name_2": "BXD68", 
    "se": 0.408708, 
    "value": 8.075
  }, 
  {
    "data_id": 71606570, 
    "sample_name": "BXD69", 
    "sample_name_2": "BXD69", 
    "se": 0.399515, 
    "value": 8.0245
  }, 
  {
    "data_id": 71606570, 
    "sample_name": "BXD70", 
    "sample_name_2": "BXD70", 
    "se": 0.370524, 
    "value": 8.154
  }, 
  {
    "data_id": 71606570, 
    "sample_name": "BXD71", 
    "sample_name_2": "BXD71", 
    "se": 0.164756, 
    "value": 8.0975
  }, 
  {
    "data_id": 71606570, 
    "sample_name": "BXD73", 
    "sample_name_2": "BXD73", 
    "se": 0.255266, 
    "value": 7.6545
  }, 
  {
    "data_id": 71606570, 
    "sample_name": "BXD73a", 
    "sample_name_2": "BXD80", 
    "se": 0.154856, 
    "value": 7.8405
  }, 
  {
    "data_id": 71606570, 
    "sample_name": "BXD73b", 
    "sample_name_2": "BXD103", 
    "se": 0.359917, 
    "value": 7.4305
  }, 
  {
    "data_id": 71606570, 
    "sample_name": "BXD75", 
    "sample_name_2": "BXD75", 
    "se": 0.206475, 
    "value": 7.963
  }, 
  {
    "data_id": 71606570, 
    "sample_name": "BXD79", 
    "sample_name_2": "BXD79", 
    "se": 0.206475, 
    "value": 7.687
  }, 
  {
    "data_id": 71606570, 
    "sample_name": "BXD83", 
    "sample_name_2": "BXD83", 
    "se": 0.0770746, 
    "value": 7.9555
  }, 
  {
    "data_id": 71606570, 
    "sample_name": "BXD84", 
    "sample_name_2": "BXD84", 
    "se": 0.0346482, 
    "value": 7.8735
  }, 
  {
    "data_id": 71606570, 
    "sample_name": "BXD85", 
    "sample_name_2": "BXD85", 
    "se": 0.548008, 
    "value": 7.8305
  }, 
  {
    "data_id": 71606570, 
    "sample_name": "BXD87", 
    "sample_name_2": "BXD87", 
    "se": 0.106066, 
    "value": 8.034
  }, 
  {
    "data_id": 71606570, 
    "sample_name": "BXD89", 
    "sample_name_2": "BXD89", 
    "se": 0.224153, 
    "value": 7.8985
  }, 
  {
    "data_id": 71606570, 
    "sample_name": "BXD90", 
    "sample_name_2": "BXD90", 
    "se": 0.0445477, 
    "value": 7.9385
  }, 
  {
    "data_id": 71606570, 
    "sample_name": "BXD95", 
    "sample_name_2": "BXD95", 
    "se": 0.243008, 
    "value": 8.21667
  }, 
  {
    "data_id": 71606570, 
    "sample_name": "BXD99", 
    "sample_name_2": "BXD99", 
    "se": 0.792667, 
    "value": 7.8645
  }, 
  {
    "data_id": 71606570, 
    "sample_name": "C57BL/6J", 
    "sample_name_2": "C57BL/6J", 
    "se": 0.265031, 
    "value": 8.01775
  }, 
  {
    "data_id": 71606570, 
    "sample_name": "D2B6F1", 
    "sample_name_2": "D2B6F1", 
    "se": 0.138593, 
    "value": 7.761
  }, 
  {
    "data_id": 71606570, 
    "sample_name": "DBA/2J", 
    "sample_name_2": "DBA/2J", 
    "se": 0.352615, 
    "value": 8.28433
  }
]
