[
  {
    "data_id": 76505327, 
    "sample_name": "BXD1", 
    "sample_name_2": "BXD1", 
    "se": 0.0850234, 
    "value": 8.42275
  }, 
  {
    "data_id": 76505327, 
    "sample_name": "BXD100", 
    "sample_name_2": "BXD100", 
    "se": 0.240443, 
    "value": 7.89725
  }, 
  {
    "data_id": 76505327, 
    "sample_name": "BXD101", 
    "sample_name_2": "BXD101", 
    "se": 0.133682, 
    "value": 7.827
  }, 
  {
    "data_id": 76505327, 
    "sample_name": "BXD102", 
    "sample_name_2": "BXD102", 
    "se": 0.210817, 
    "value": 8.07925
  }, 
  {
    "data_id": 76505327, 
    "sample_name": "BXD11", 
    "sample_name_2": "BXD11", 
    "se": 0.126486, 
    "value": 8.542
  }, 
  {
    "data_id": 76505327, 
    "sample_name": "BXD12", 
    "sample_name_2": "BXD12", 
    "se": 0.31171, 
    "value": 8.16375
  }, 
  {
    "data_id": 76505327, 
    "sample_name": "BXD13", 
    "sample_name_2": "BXD13", 
    "se": 0.144294, 
    "value": 8.4095
  }, 
  {
    "data_id": 76505327, 
    "sample_name": "BXD14", 
    "sample_name_2": "BXD14", 
    "se": 0.401215, 
    "value": 7.83675
  }, 
  {
    "data_id": 76505327, 
    "sample_name": "BXD15", 
    "sample_name_2": "BXD15", 
    "se": 0.0627606, 
    "value": 8.504
  }, 
  {
    "data_id": 76505327, 
    "sample_name": "BXD16", 
    "sample_name_2": "BXD16", 
    "se": 0.145441, 
    "value": 8.0565
  }, 
  {
    "data_id": 76505327, 
    "sample_name": "BXD18", 
    "sample_name_2": "BXD18", 
    "se": 0.0696393, 
    "value": 8.23125
  }, 
  {
    "data_id": 76505327, 
    "sample_name": "BXD19", 
    "sample_name_2": "BXD19", 
    "se": 0.200551, 
    "value": 7.96
  }, 
  {
    "data_id": 76505327, 
    "sample_name": "BXD2", 
    "sample_name_2": "BXD2", 
    "se": 0.192703, 
    "value": 7.99125
  }, 
  {
    "data_id": 76505327, 
    "sample_name": "BXD20", 
    "sample_name_2": "BXD20", 
    "se": 0.246348, 
    "value": 7.863
  }, 
  {
    "data_id": 76505327, 
    "sample_name": "BXD21", 
    "sample_name_2": "BXD21", 
    "se": 0.0860909, 
    "value": 8.00625
  }, 
  {
    "data_id": 76505327, 
    "sample_name": "BXD22", 
    "sample_name_2": "BXD22", 
    "se": 0.158207, 
    "value": 8.2895
  }, 
  {
    "data_id": 76505327, 
    "sample_name": "BXD27", 
    "sample_name_2": "BXD27", 
    "se": 0.175902, 
    "value": 8.1055
  }, 
  {
    "data_id": 76505327, 
    "sample_name": "BXD28", 
    "sample_name_2": "BXD28", 
    "se": 0.0184572, 
    "value": 8.33567
  }, 
  {
    "data_id": 76505327, 
    "sample_name": "BXD29", 
    "sample_name_2": "BXD29", 
    "se": 0.108408, 
    "value": 8.373
  }, 
  {
    "data_id": 76505327, 
    "sample_name": "BXD31", 
    "sample_name_2": "BXD31", 
    "se": 0.0730409, 
    "value": 8.17825
  }, 
  {
    "data_id": 76505327, 
    "sample_name": "BXD33", 
    "sample_name_2": "BXD33", 
    "se": 0.302155, 
    "value": 8.36025
  }, 
  {
    "data_id": 76505327, 
    "sample_name": "BXD34", 
    "sample_name_2": "BXD34", 
    "se": 0.100699, 
    "value": 8.058
  }, 
  {
    "data_id": 76505327, 
    "sample_name": "BXD36", 
    "sample_name_2": "BXD36", 
    "se": 0.204992, 
    "value": 8.57825
  }, 
  {
    "data_id": 76505327, 
    "sample_name": "BXD38", 
    "sample_name_2": "BXD38", 
    "se": 0.130442, 
    "value": 8.28
  }, 
  {
    "data_id": 76505327, 
    "sample_name": "BXD39", 
    "sample_name_2": "BXD39", 
    "se": 0.340651, 
    "value": 8.1695
  }, 
  {
    "data_id": 76505327, 
    "sample_name": "BXD40", 
    "sample_name_2": "BXD40", 
    "se": 0.157754, 
    "value": 7.968
  }, 
  {
    "data_id": 76505327, 
    "sample_name": "BXD42", 
    "sample_name_2": "BXD42", 
    "se": 0.0888574, 
    "value": 8.40625
  }, 
  {
    "data_id": 76505327, 
    "sample_name": "BXD43", 
    "sample_name_2": "BXD43", 
    "se": 0.219366, 
    "value": 8.11625
  }, 
  {
    "data_id": 76505327, 
    "sample_name": "BXD48", 
    "sample_name_2": "BXD48", 
    "se": 0.32314, 
    "value": 8.03325
  }, 
  {
    "data_id": 76505327, 
    "sample_name": "BXD48a", 
    "sample_name_2": "BXD96", 
    "se": 0.0183848, 
    "value": 8.133
  }, 
  {
    "data_id": 76505327, 
    "sample_name": "BXD5", 
    "sample_name_2": "BXD5", 
    "se": 0.284757, 
    "value": 7.65725
  }, 
  {
    "data_id": 76505327, 
    "sample_name": "BXD50", 
    "sample_name_2": "BXD50", 
    "se": 0.102398, 
    "value": 8.38425
  }, 
  {
    "data_id": 76505327, 
    "sample_name": "BXD51", 
    "sample_name_2": "BXD51", 
    "se": 0.118149, 
    "value": 7.80675
  }, 
  {
    "data_id": 76505327, 
    "sample_name": "BXD56", 
    "sample_name_2": "BXD56", 
    "se": 0.129579, 
    "value": 8.28575
  }, 
  {
    "data_id": 76505327, 
    "sample_name": "BXD6", 
    "sample_name_2": "BXD6", 
    "se": 0.328099, 
    "value": 8.2755
  }, 
  {
    "data_id": 76505327, 
    "sample_name": "BXD60", 
    "sample_name_2": "BXD60", 
    "se": 0.142832, 
    "value": 7.789
  }, 
  {
    "data_id": 76505327, 
    "sample_name": "BXD63", 
    "sample_name_2": "BXD63", 
    "se": 0.19713, 
    "value": 8.18125
  }, 
  {
    "data_id": 76505327, 
    "sample_name": "BXD65", 
    "sample_name_2": "BXD65", 
    "se": 0.0763654, 
    "value": 7.9775
  }, 
  {
    "data_id": 76505327, 
    "sample_name": "BXD65b", 
    "sample_name_2": "BXD92", 
    "se": 0.324516, 
    "value": 8.0625
  }, 
  {
    "data_id": 76505327, 
    "sample_name": "BXD67", 
    "sample_name_2": "BXD67", 
    "se": 0.0957595, 
    "value": 8.2715
  }, 
  {
    "data_id": 76505327, 
    "sample_name": "BXD69", 
    "sample_name_2": "BXD69", 
    "se": 0.112796, 
    "value": 7.95325
  }, 
  {
    "data_id": 76505327, 
    "sample_name": "BXD71", 
    "sample_name_2": "BXD71", 
    "se": 0.216537, 
    "value": 8.05225
  }, 
  {
    "data_id": 76505327, 
    "sample_name": "BXD73", 
    "sample_name_2": "BXD73", 
    "se": 0.180307, 
    "value": 8.088
  }, 
  {
    "data_id": 76505327, 
    "sample_name": "BXD75", 
    "sample_name_2": "BXD75", 
    "se": 0.186523, 
    "value": 8.45775
  }, 
  {
    "data_id": 76505327, 
    "sample_name": "BXD8", 
    "sample_name_2": "BXD8", 
    "se": 0.446908, 
    "value": 7.5725
  }, 
  {
    "data_id": 76505327, 
    "sample_name": "BXD84", 
    "sample_name_2": "BXD84", 
    "se": 0.149122, 
    "value": 8.22
  }, 
  {
    "data_id": 76505327, 
    "sample_name": "BXD85", 
    "sample_name_2": "BXD85", 
    "se": 0.0653323, 
    "value": 8.17475
  }, 
  {
    "data_id": 76505327, 
    "sample_name": "BXD86", 
    "sample_name_2": "BXD86", 
    "se": 0.205991, 
    "value": 8.016
  }, 
  {
    "data_id": 76505327, 
    "sample_name": "BXD87", 
    "sample_name_2": "BXD87", 
    "se": 0.0496297, 
    "value": 8.222
  }, 
  {
    "data_id": 76505327, 
    "sample_name": "BXD9", 
    "sample_name_2": "BXD9", 
    "se": 0.142018, 
    "value": 8.325
  }, 
  {
    "data_id": 76505327, 
    "sample_name": "BXD90", 
    "sample_name_2": "BXD90", 
    "se": 0.166014, 
    "value": 8.28725
  }, 
  {
    "data_id": 76505327, 
    "sample_name": "BXD99", 
    "sample_name_2": "BXD99", 
    "se": 0.108886, 
    "value": 8.214
  }, 
  {
    "data_id": 76505327, 
    "sample_name": "C57BL/6J", 
    "sample_name_2": "C57BL/6J", 
    "se": 0.0670909, 
    "value": 8.01075
  }, 
  {
    "data_id": 76505327, 
    "sample_name": "DBA/2J", 
    "sample_name_2": "DBA/2J", 
    "se": 0.124008, 
    "value": 8.1495
  }
]
