[
  {
    "data_id": 71767326, 
    "sample_name": "B6D2F1", 
    "sample_name_2": "B6D2F1", 
    "se": 0.225567, 
    "value": 7.3825
  }, 
  {
    "data_id": 71767326, 
    "sample_name": "BXD1", 
    "sample_name_2": "BXD1", 
    "se": 0.255973, 
    "value": 7.908
  }, 
  {
    "data_id": 71767326, 
    "sample_name": "BXD100", 
    "sample_name_2": "BXD100", 
    "se": 0.251023, 
    "value": 7.4125
  }, 
  {
    "data_id": 71767326, 
    "sample_name": "BXD101", 
    "sample_name_2": "BXD101", 
    "se": 0.0233345, 
    "value": 5.8825
  }, 
  {
    "data_id": 71767326, 
    "sample_name": "BXD102", 
    "sample_name_2": "BXD102", 
    "se": 0.435578, 
    "value": 7.178
  }, 
  {
    "data_id": 71767326, 
    "sample_name": "BXD11", 
    "sample_name_2": "BXD11", 
    "se": 1.08965, 
    "value": 7.2685
  }, 
  {
    "data_id": 71767326, 
    "sample_name": "BXD12", 
    "sample_name_2": "BXD12", 
    "se": 0.214253, 
    "value": 7.1545
  }, 
  {
    "data_id": 71767326, 
    "sample_name": "BXD14", 
    "sample_name_2": "BXD14", 
    "se": 1.51392, 
    "value": 7.0835
  }, 
  {
    "data_id": 71767326, 
    "sample_name": "BXD24", 
    "sample_name_2": "BXD24", 
    "se": 0.250316, 
    "value": 6.205
  }, 
  {
    "data_id": 71767326, 
    "sample_name": "BXD27", 
    "sample_name_2": "BXD27", 
    "se": 0.387495, 
    "value": 7.551
  }, 
  {
    "data_id": 71767326, 
    "sample_name": "BXD29", 
    "sample_name_2": "BXD29", 
    "se": 0.774989, 
    "value": 7.004
  }, 
  {
    "data_id": 71767326, 
    "sample_name": "BXD31", 
    "sample_name_2": "BXD31", 
    "se": 1.154, 
    "value": 6.833
  }, 
  {
    "data_id": 71767326, 
    "sample_name": "BXD32", 
    "sample_name_2": "BXD32", 
    "se": 0.830143, 
    "value": 7.01
  }, 
  {
    "data_id": 71767326, 
    "sample_name": "BXD34", 
    "sample_name_2": "BXD34", 
    "se": 0.332357, 
    "value": 7.10133
  }, 
  {
    "data_id": 71767326, 
    "sample_name": "BXD39", 
    "sample_name_2": "BXD39", 
    "se": 0.0565685, 
    "value": 7.259
  }, 
  {
    "data_id": 71767326, 
    "sample_name": "BXD40", 
    "sample_name_2": "BXD40", 
    "se": 0.0233345, 
    "value": 6.4465
  }, 
  {
    "data_id": 71767326, 
    "sample_name": "BXD42", 
    "sample_name_2": "BXD42", 
    "se": 0.0975807, 
    "value": 7.346
  }, 
  {
    "data_id": 71767326, 
    "sample_name": "BXD43", 
    "sample_name_2": "BXD43", 
    "se": 0.219768, 
    "value": 7.28667
  }, 
  {
    "data_id": 71767326, 
    "sample_name": "BXD44", 
    "sample_name_2": "BXD44", 
    "se": 0.251993, 
    "value": 6.7788
  }, 
  {
    "data_id": 71767326, 
    "sample_name": "BXD45", 
    "sample_name_2": "BXD45", 
    "se": 0.16122, 
    "value": 7.098
  }, 
  {
    "data_id": 71767326, 
    "sample_name": "BXD48", 
    "sample_name_2": "BXD48", 
    "se": 0.072832, 
    "value": 7.4305
  }, 
  {
    "data_id": 71767326, 
    "sample_name": "BXD49", 
    "sample_name_2": "BXD49", 
    "value": 6.298
  }, 
  {
    "data_id": 71767326, 
    "sample_name": "BXD50", 
    "sample_name_2": "BXD50", 
    "se": 0.634982, 
    "value": 7.186
  }, 
  {
    "data_id": 71767326, 
    "sample_name": "BXD56", 
    "sample_name_2": "BXD56", 
    "se": 0.174963, 
    "value": 7.10867
  }, 
  {
    "data_id": 71767326, 
    "sample_name": "BXD60", 
    "sample_name_2": "BXD60", 
    "se": 0.199404, 
    "value": 6.436
  }, 
  {
    "data_id": 71767326, 
    "sample_name": "BXD62", 
    "sample_name_2": "BXD62", 
    "se": 0.195869, 
    "value": 7.3635
  }, 
  {
    "data_id": 71767326, 
    "sample_name": "BXD63", 
    "sample_name_2": "BXD63", 
    "se": 0.433456, 
    "value": 7.8385
  }, 
  {
    "data_id": 71767326, 
    "sample_name": "BXD65", 
    "sample_name_2": "BXD65", 
    "se": 0.792667, 
    "value": 6.7085
  }, 
  {
    "data_id": 71767326, 
    "sample_name": "BXD65a", 
    "sample_name_2": "BXD97", 
    "se": 0.86762, 
    "value": 7.5295
  }, 
  {
    "data_id": 71767326, 
    "sample_name": "BXD65b", 
    "sample_name_2": "BXD92", 
    "se": 0.405172, 
    "value": 7.7985
  }, 
  {
    "data_id": 71767326, 
    "sample_name": "BXD68", 
    "sample_name_2": "BXD68", 
    "se": 0.688722, 
    "value": 7.852
  }, 
  {
    "data_id": 71767326, 
    "sample_name": "BXD69", 
    "sample_name_2": "BXD69", 
    "se": 0.0388909, 
    "value": 7.6445
  }, 
  {
    "data_id": 71767326, 
    "sample_name": "BXD70", 
    "sample_name_2": "BXD70", 
    "se": 0.130815, 
    "value": 7.6325
  }, 
  {
    "data_id": 71767326, 
    "sample_name": "BXD71", 
    "sample_name_2": "BXD71", 
    "se": 0.0982878, 
    "value": 7.7095
  }, 
  {
    "data_id": 71767326, 
    "sample_name": "BXD73", 
    "sample_name_2": "BXD73", 
    "se": 1.9601, 
    "value": 6.61
  }, 
  {
    "data_id": 71767326, 
    "sample_name": "BXD73a", 
    "sample_name_2": "BXD80", 
    "se": 0.890955, 
    "value": 6.86
  }, 
  {
    "data_id": 71767326, 
    "sample_name": "BXD73b", 
    "sample_name_2": "BXD103", 
    "se": 1.20703, 
    "value": 6.5145
  }, 
  {
    "data_id": 71767326, 
    "sample_name": "BXD75", 
    "sample_name_2": "BXD75", 
    "se": 1.0444, 
    "value": 7.5245
  }, 
  {
    "data_id": 71767326, 
    "sample_name": "BXD79", 
    "sample_name_2": "BXD79", 
    "se": 0.422143, 
    "value": 6.1685
  }, 
  {
    "data_id": 71767326, 
    "sample_name": "BXD83", 
    "sample_name_2": "BXD83", 
    "se": 0.0933381, 
    "value": 7.742
  }, 
  {
    "data_id": 71767326, 
    "sample_name": "BXD84", 
    "sample_name_2": "BXD84", 
    "se": 0.852771, 
    "value": 7.095
  }, 
  {
    "data_id": 71767326, 
    "sample_name": "BXD85", 
    "sample_name_2": "BXD85", 
    "se": 0.509824, 
    "value": 6.4875
  }, 
  {
    "data_id": 71767326, 
    "sample_name": "BXD87", 
    "sample_name_2": "BXD87", 
    "se": 0.142128, 
    "value": 7.1345
  }, 
  {
    "data_id": 71767326, 
    "sample_name": "BXD89", 
    "sample_name_2": "BXD89", 
    "se": 0.342947, 
    "value": 7.2055
  }, 
  {
    "data_id": 71767326, 
    "sample_name": "BXD90", 
    "sample_name_2": "BXD90", 
    "se": 0.494268, 
    "value": 7.4605
  }, 
  {
    "data_id": 71767326, 
    "sample_name": "BXD95", 
    "sample_name_2": "BXD95", 
    "se": 0.789077, 
    "value": 7.37533
  }, 
  {
    "data_id": 71767326, 
    "sample_name": "BXD99", 
    "sample_name_2": "BXD99", 
    "se": 0.403051, 
    "value": 7.419
  }, 
  {
    "data_id": 71767326, 
    "sample_name": "C57BL/6J", 
    "sample_name_2": "C57BL/6J", 
    "se": 0.124779, 
    "value": 7.3795
  }, 
  {
    "data_id": 71767326, 
    "sample_name": "D2B6F1", 
    "sample_name_2": "D2B6F1", 
    "se": 0.660438, 
    "value": 7.066
  }, 
  {
    "data_id": 71767326, 
    "sample_name": "DBA/2J", 
    "sample_name_2": "DBA/2J", 
    "se": 0.582797, 
    "value": 7.26067
  }
]
